Workbook

Sheet Dataset
A1: Country | B1: Sector | C1: Sub-Sector | D1: Application Sector | E1: Entity Type | F1: Entity / Innovation Name | G1: Key Innovation / Description | H1: Information Type | I1: Reference Date | J1: Last Verified | K1: Recent Funding | L1: Source Name | M1: Source Type | N1: Source URL | O1: Verification Status | P1: Notes
A2: Algeria | B2: Policy | C2: Legal Frameworks | D2: Government | E2: Policy | F2: Algeria Startup Act (startup.dz) | G2: State program providing digital labeling portals, tax exemptions and direct subsidies. | H2: Guidelines | I2: 2020-10-01 | J2: 2026-07-22 | K2: N/A | L2: Algerian Government | M2: Primary | N2: https://www.startup.dz/ | O2: Verified | P2: Verified: startup.dz is the official national portal; Executive Decree 20-254 created the National Committee for Labelling Startups/Innovative Projects/Incubators; Finance Law 2020 grants labelled startups a 2-year exemption from TAP & IBS plus VAT/reduced-customs relief. Corroborated by LaunchBase Africa (2,300+ startups labelled by 2024).
A3: Algeria | B3: Fintech | C3: Insurtech | D3: Finance | E3: Hub | F3: Insurance Innovation and AI Hub (Sidi Abdallah) | G3: Academic and state sandbox coordinating the integration of AI models, claims automation, and actuarial machine learning. the hub is designed to stimulate innovation within the insurance sector by integrating AI applications, promoting applied research, and enabling experimentation with new digital solutions. | H3: News article | I3: 2026-01-08 | J3: 2026-07-08 | K3: N/A | L3: Dzair AI News | M3: Primary (News) | N3: https://dzair-ai.org/community/news/2026-01-08_Insurance_AI_Innovation_Hub_Sidi_Abdallah | O3: Verified
A4: Algeria | B4: Enterprise AI | C4: Cybersecurity | D4: Industry | E4: Hub | F4: AI & Cybersecurity Start-up Cluster (Sidi Abdallah) | G4: University-centric incubator bridging the industry-academia gap to accelerate the commercialization of research. | H4: News article | I4: 2026-04-21 | J4: 2026-07-08 | K4: N/A | L4: Africa AI News | M4: Primary (News) | N4: https://www.africaainews.com/p/algeria-launches-first-ai-and-cybersecurity-v2 | O4: Verified
A5: Algeria | B5: General | C5: Academic Infrastructure | D5: Education | E5: Hub | F5: Abdelhafid Ihaddaden Scientific and Technology Hub | G5: An 87-hectare science park housing core institutions like ENSIA to coordinate computer science research. | H5: Hub overview | I5: 2024 | J5: 2026-07-08 | K5: N/A | L5: Africa AI News | M5: Primary (News) | N5: https://www.africaainews.com/p/algeria-launches-first-ai-and-cybersecurity-v2 | O5: Verified
A6: Algeria | B6: Policy | C6: National Strategy | D6: Education | E6: Policy | F6: National School of Artificial Intelligence (ENSIA) | G6: A specialized state academy established to stimulate academic research in AI and cultivate national engineering talent. | H6: Institution details | I6: 2020 | J6: 2026-07-08 | K6: N/A | L6: AIWorld.eu (Country Profile) | M6: Aggregator | N6: https://www.aiworld.eu/geo/algeria | O6: Verified
A7: Algeria | B7: General | C7: Academic Infrastructure | D7: Education | E7: Hub | F7: CERIST | G7: Key scientific institution coordinating national university networks and research in basic scientific computing. | H7: Research profile | I7: 2025 | J7: 2026-07-08 | K7: N/A | L7: AIWorld.eu (Country Profile) | M7: Aggregator | N7: https://www.aiworld.eu/geo/algeria | O7: Verified
A8: Algeria | B8: General | C8: Ecosystem Statistics | D8: Cross-sector | E8: Policy | F8: CEPS AI World Country Profile (Algeria) | G8: Macroeconomic tracking index compiling national parameters such as the $7 million in annual AI investments. | H8: Ecosystem statistics | I8: 2026-01-01 | J8: 2026-07-08 | K8: $7,000,000 | L8: AIWorld.eu (Country Profile) | M8: Aggregator | N8: https://www.aiworld.eu/geo/algeria | O8: Verified
A9: Algeria | B9: Enterprise AI | C9: Autonomous Logistics | D9: Industry | E9: Startup | F9: Yassir | G9: A regional super-application deploying geospatial AI and route optimization engines for carpooling and logistics. | H9: Company Profile | I9: Not specified | J9: 2026-07-08 | K9: $150,000,000 | L9: Company website (Yassir) | M9: Primary | N9: https://yassir.com/ | O9: Verified
A10: Algeria | B10: Policy | C10: Legal Frameworks | D10: Government | E10: Policy | F10: Law 18-07 (Data Protection Authority) | G10: Enacted law and administrative authority designed to regulate personal data use and ensure compliance. | H10: Regulatory law text | I10: 2023 | J10: 2026-07-10 | K10: N/A | L10: Africa Business Intelligence | M10: Primary (News) | N10: https://www.africa-bi.com/fr/article/actualite/algerie-transformation-digitale-l-enjeu-de-la-securite-et-de-la-protection-des-donnees | O10: Verified | P10: Re-sourced: original Cambridge academic-survey citation confirmed accurate but was 2nd-hand; swapped to the primary news source the paper itself cites
A11: Egypt | B11: Policy | C11: National Strategy | D11: Government | E11: Policy | F11: Egypt National AI Strategy (MCIT) | G11: State strategy focused on capacity building, talent training and AI applications in the public sector. | H11: Strategic document (PDF) | I11: 2021-07-01 | J11: 2026-07-08 | K11: N/A | L11: Egyptian Government (MCIT) | M11: Primary (Government) | N11: https://ai.gov.eg/Egypt%20National%20AI%20Strategy-%20English.pdf | O11: Verified
A12: Egypt | B12: Enterprise AI | C12: Credit Scoring | D12: Finance | E12: Startup | F12: Synapse Analytics | G12: AI-based credit scoring engines and risk management algorithms that automate lending decisions. | H12: Product specifications | I12: 2018 | J12: 2026-07-22 | K12: $2,000,000 | L12: Company website (Synapse Analytics) | M12: Primary | N12: https://synapse-analytics.io/ | O12: Verified | P12: Verified: founded 2018 by Ahmed Abaza & Galal El Beshbishy; flagship 'Konan' MLOps/AI credit-scoring platform; raised $2M (2024) led by Silicon Badia & Hub71; Aug-2025 partnership with credit bureau iScore for an AI credit-decisioning platform. Funding updated Undisclosed -> $2,000,000; ref date set to founding year.
A13: Egypt | B13: General | C13: Venture Capital | D13: Finance | E13: Investor | F13: Flat6Labs | G13: Prominent seed investor and accelerator of technology startups operating structured programs across Cairo. | H13: Investment portfolio | I13: Not specified | J13: 2026-07-08 | K13: N/A | L13: Company website (Flat6Labs) | M13: Primary | N13: https://www.flat6labs.com/ | O13: Verified
A14: Egypt | B14: Healthtech | C14: Imaging | D14: Healthcare | E14: Startup | F14: Intixel | G14: Medical image processing software using AI to assist radiologists in the early detection of breast cancer. | H14: Company Profile | I14: Not specified | J14: 2026-07-08 | K14: Undisclosed | L14: Company website (Intixel) | M14: Primary | N14: https://intixel.com/ | O14: Verified
A15: Egypt | B15: Enterprise AI | C15: Professional Networking | D15: Industry | E15: Startup | F15: BrainsMingle | G15: Professional AI-powered networking platform integrating private in-house hubs for face-to-face interactions and live mentoring. | H15: Company Profile | I15: 2024 | J15: 2026-07-08 | K15: Undisclosed | L15: LinkedIn | M15: Aggregator | N15: https://www.linkedin.com/company/brainsmingle | O15: Verified
A16: Egypt | B16: Enterprise AI | C16: Semiconductors & AI Infrastructure | D16: Industry | E16: Startup | F16: InfiniLink | G16: Development of high-speed optical transceiver engines for Ethernet, PCIe and AI applications (Acquired by GlobalFoundries). | H16: M&A Acquisition Data | I16: 2022 | J16: 2026-07-08 | K16: Undisclosed | L16: LinkedIn | M16: Aggregator | N16: https://www.linkedin.com/company/infinilink/ | O16: Verified
A17: Egypt | B17: Healthtech | C17: Pharmaceutical Supply Chain | D17: Healthcare | E17: Startup | F17: Grinta | G17: End-to-end managed B2B marketplace using AI to trace medical products and empower independent local pharmacies. | H17: Product specifications | I17: 2021 | J17: 2026-07-08 | K17: Undisclosed | L17: Crunchbase | M17: Aggregator | N17: https://www.crunchbase.com/organization/grinta | O17: Verified
A18: Egypt | B18: Policy | C18: National Strategy | D18: Government | E18: Policy | F18: National Council of Artificial Intelligence | G18: Governmental body established to craft, structure, and oversee the execution of Egypt's national AI strategy. | H18: Government Policy Document | I18: 2019 | J18: 2026-07-10 | K18: N/A | L18: Cambridge University Press (Data & Policy journal) | M18: Secondary (Academic Survey) | N18: https://www.cambridge.org/core/journals/data-and-policy/article/exploring-ai-governance-in-the-middle-east-and-north-africa-mena-region-gaps-efforts-and-initiatives/867858AA465EEB06B5C43FF7048D8652 | O18: Verified | P18: Fetched and confirmed: paper states Egypt established National Council for AI in 2019
A19: Egypt | B19: General | C19: Incubation | D19: Cross-sector | E19: Hub | F19: The AI Campus (New Cairo) | G19: 500-acre AI Campus at Sumou Boulevard, New Cairo, launched via an MoU between Orange Egypt and real-estate developer Paragon | Adeer, in partnership with Plug and Play's global innovation network. Orange Egypt leads smart digital infrastructure (5G, IoT, intelligent communications). Includes the "AI 100" program, a four-year initiative to support the creation of 100 AI startups in Egypt by 2030 through training, technical workshops, and investment-readiness support. | H19: Corporate Briefing | I19: 2026-04-20 | J19: 2026-07-17 | K19: N/A | L19: Company website (Orange Egypt) | M19: Primary | N19: https://www.orange.eg/en/about/media-center/press-kit/orange-and-paragon-development-partnership-891-event | O19: Verified
A20: Egypt | B20: General | C20: Ecosystem Event | D20: Cross-sector | E20: Hub | F20: Ai Everything MEA (Egypt Edition) | G20: The Ai Everything MEA (Egypt Edition) hub acts as a cross-sector launchpad designed to accelerate collaborative AI research, startup scaling, and digital capacity-building across the Middle East and Africa. Aligned with Egypt's National AI Strategy, the hub focuses on key innovations like AI-as-a-Service (AIaaS) infrastructure, advanced data centers optimized for high-performance workloads, and predictive AI cybersecurity systems. Additionally, it features pioneering regional applications such as deep-tech solutions for enterprise digital supply chains, specialized biotech and digital healthcare diagnostics, and local large language models (LLMs)-cementing Cairo's role as a vital center for economic and societal transformation through AI. | H20: Exhibition Records | I20: 2026 | J20: 2026-07-09 | K20: N/A | L20: Ai Everything MEA (event site) | M20: Primary | N20: https://www.aieverything.com/ | O20: Verified
A21: Egypt | B21: Enterprise AI | C21: NLP | D21: Industry | E21: Startup | F21: WideBot | G21: Platform for building Arabic-focused chatbots capable of detecting sentiment and slang nuances. | H21: Company website | I21: 2025 | J21: 2026-07-09 | K21: Undisclosed | L21: Company website (WideBot) | M21: Primary | N21: https://widebot.net/ | O21: Verified
A22: Egypt | B22: Enterprise AI | C22: Conversational AI | D22: Industry | E22: Startup | F22: Olimi AI | G22: Multilingual voice agents capable of handling complex customer calls in local Arabic dialects. | H22: Company Profile | I22: 2026 | J22: 2026-07-09 | K22: Undisclosed | L22: Crunchbase | M22: Aggregator | N22: https://www.crunchbase.com/organization/olimi | O22: Verified | P22: Source Type corrected from 'Primary' to 'Aggregator' for consistency with other Crunchbase-sourced rows
A23: Egypt | B23: Enterprise AI | C23: NLP | D23: Industry | E23: Startup | F23: DXwand | G23: Generative AI platform used by contact centers to automate customer interactions with high accuracy. | H23: Company website | I23: 2026 | J23: 2026-07-09 | K23: Undisclosed | L23: Company website (DXwand) | M23: Primary | N23: https://www.dxwand.com/ | O23: Verified | P23: Source Name corrected to match URL domain
A24: Egypt | B24: Healthtech | C24: Imaging | D24: Healthcare | E24: Startup | F24: Rology | G24: On-demand teleradiology platform integrating Artificial Intelligence directly into both the clinical and operational layers of teleradiology. connecting hospitals with remote radiologists using AI. | H24: Company website | I24: 2023 | J24: 2026-07-09 | K24: Undisclosed | L24: Company website (Rology) | M24: Primary | N24: https://rology.health/ | O24: Verified | P24: Source Name corrected to match URL domain
A25: Egypt | B25: Healthtech | C25: Diagnostics | D25: Healthcare | E25: Startup | F25: DilenyTech | G25: Specializes in AI-enabled breast imaging to improve cancer detection rates and reduce diagnostic errors. | H25: linkedin | I25: 2021 | J25: 2026-07-09 | K25: Undisclosed | L25: LinkedIn | M25: Primary | N25: https://www.linkedin.com/company/dilenytech | O25: Verified
A26: Egypt | B26: Healthtech | C26: Diagnostics | D26: Healthcare | E26: Startup | F26: IRRI Vision | G26: Equips doctors with AI diagnostic tools to sharpen clinical decision-making. Acquired by Edafa VC. | H26: Deal Announcements | I26: 2024 | J26: 2026-07-09 | K26: Undisclosed | L26: Morocco World news | M26: Aggregator | N26: https://www.moroccoworldnews.com/2026/02/278634/ai-everything-mea-egypt-concludes-with-real-world-ai-deployment-strong-message-of-regions-momentum/ | O26: Verified | P26: Source Type corrected to 'Aggregator'; recommend cross-checking against Edafa VC's own deal announcement
A27: Egypt | B27: Agritech | C27: Biotech | D27: Agriculture | E27: Startup | F27: Al Protein | G27: Biotech startup using AI and IoT sensors to farm duckweed in desert environments for sustainable protein. | H27: Company Profile | I27: 2024 | J27: 2026-07-09 | K27: Undisclosed | L27: Crunchbase | M27: Aggregator | N27: https://www.crunchbase.com/organization/al-protein | O27: Verified
A28: Egypt | B28: Agritech | C28: Precision Farming | D28: Agriculture | E28: Startup | F28: AgriCan | G28: AI and IoT-driven agricultural robotics startup founded in 2020 by Salem Ghanam, motivated by farmers suffering pesticide-related health issues. Pivoted from drone-based to ground-based robots in 2022. Deployed across 5,230 acres on 15+ Egyptian farms, expanded to UAE and Jordan. Offers precision pesticide spraying, portable plant disease detection, and greenhouse soil/salinity/CO2 monitoring. Represented Egypt at COP28; field trials showed 15% higher yields, 31% less pesticide use, 12% less labor. | H28: Company Profile | I28: 2025 | J28: 2026-07-09 | K28: Undisclosed | L28: TechCabl | M28: Aggregator | N28: https://techcabal.com/2025/03/26/agrican-robots-make-farming-smarter/ | O28: Verified | P28: Cleaned malformed source URL (removed leading ', ') so the citation is a valid clickable link.
A29: Egypt | B29: Policy | C29: National Strategy | D29: Government | E29: Policy | F29: Karnak (formerly 'Arabic Brain') | G29: LLM trained on Egyptian and Arab data to ensure cultural relevance and data sovereignty. | H29: Official strategic document | I29: 2026 | J29: 2026-07-09 | K29: N/A | L29: Egyptian Government (MCIT) | M29: Primary (Government) | N29: https://mcit.gov.eg/en/National_AI_Strategy | O29: Verified
A30: Egypt | B30: Enterprise AI | C30: Construction Tech | D30: Industry | E30: Startup | F30: Kuadra | G30: Applying AI and develops scalable SaaS solutions designed to structure workflows, integrate data, and improve decision-making for the planning and execution of large-scale construction projects. Acquired by Edafa VC. | H30: Deal Announcements | I30: 2026 | J30: 2026-07-09 | K30: Undisclosed | L30: LinkedIn | M30: Aggregator | N30: https://www.linkedin.com/company/kuadraai | O30: Verified
A31: Egypt | B31: Fintech | C31: Credit Scoring | D31: Finance | E31: Startup | F31: MNT-Halan | G31: FinTech unicorn utilizing advanced machine learning for credit scoring and fraud prevention. | H31: Company website | I31: 2024 | J31: 2026-07-09 | K31: Undisclosed | L31: Company website (MNT-Halan) | M31: Primary | N31: https://mnt-halan.com/ | O31: Verified | P31: Independently ranked #1 unicorn in Cairo by StartupBlink (startupblink.com/unicorn/mnt-halan), corroborating its FinTech-unicorn status.
A32: Egypt | B32: Enterprise AI | C32: Logistics & Transportation | D32: Industry | E32: Startup | F32: Trella | G32: AI-driven B2B technology platform connecting shippers with carriers, optimizing routes and pricing. | H32: Company Profile | I32: 2018 | J32: 2026-07-09 | K32: $42,000,000 | L32: Crunchbase | M32: Aggregator | N32: https://www.crunchbase.com/organization/trella | O32: Verified
A33: Egypt | B33: Policy | C33: Tech Development | D33: Government | E33: Policy | F33: ITIDA | G33: Executive IT arm of the Ministry of Communications fostering AI startup incubation and digital capacity building. | H33: Government Portal | I33: 2025 | J33: 2026-07-09 | K33: N/A | L33: Egyptian Government (ITIDA) | M33: Primary (Government) | N33: https://itida.gov.eg/ | O33: Verified
A34: Egypt | B34: Enterprise AI | C34: Retail & Supply Chain | D34: Industry | E34: Startup | F34: Brimore | G34: Social commerce platform leveraging machine learning to predict demand, optimize supply chain, and match distributors. | H34: Company Profile | I34: 2017 | J34: 2026-07-09 | K34: $25,000,000 | L34: Crunchbase | M34: Aggregator | N34: https://www.crunchbase.com/organization/brimore | O34: Verified
A35: Egypt | B35: Agritech | C35: Energy & Utilities | D35: Energy | E35: Startup | F35: KarmSolar | G35: Solar technology and integration company utilizing AI algorithms to optimize microgrid power distribution and solar yields. | H35: Company Profile | I35: 2021 | J35: 2026-07-09 | K35: Undisclosed | L35: Crunchbase | M35: Aggregator | N35: https://www.crunchbase.com/organization/karmsolar | O35: Verified
A36: Lebanon | B36: Policy | C36: National Strategy | D36: Government | E36: Policy | F36: National Digital Transformation and AI Strategy 2025-2030 | G36: National strategy launched 7 Nov 2025 at the Lebanon Tech, AI and Innovation Summit by the Minister of State for Technology and AI, under the patronage of PM Nawaf Salam, covering digital government, AI adoption and ecosystem development. | H36: Government strategy | I36: 2025-11-07 | J36: 2026-08-09 | L36: Ministry of State for Technology and AI (MITAI) | M36: Primary (Government) | N36: https://www.mitai.gov.lb/ | O36: Verified | P36: Launch date, minister (Kamal Shehadi) and summit venue corroborated by Levellers.ai country review; full strategy presentation published on mitai.gov.lb.
A37: Lebanon | B37: Policy | C37: National Strategy | D37: Government | E37: Policy | F37: Ministry of State for Technology and Artificial Intelligence (MITAI / OMSITAI) | G37: Ministerial office established in 2025 by the Salam government to lead Lebanon's digital transformation and AI agenda: national digital ID, digitised payments, data exchange and AI ecosystem building. | H37: Government body | I37: 2025 | J37: 2026-08-09 | L37: Consultancy-me | M37: Primary (News) | N37: https://www.consultancy-me.com/news/11533/lebanons-government-taps-roland-berger-to-help-advance-its-ai-ambitions | O37: Verified
A38: Lebanon | B38: Policy | C38: National Strategy | D38: Government | E38: Policy | F38: OMSITAI - Roland Berger AI advisory partnership | G38: MoU under which Roland Berger (Beirut office) advises the government on AI-driven initiatives; reported alongside a planned $30-50M 2025-2026 investment in generative AI and digital public infrastructure (digital ID, payments, data exchange, 'Super App') with World Bank backing. | H38: MoU announcement | I38: 2025-08 | J38: 2026-08-09 | L38: Consultancy-me | M38: Primary (News) | N38: https://www.consultancy-me.com/news/11533/lebanons-government-taps-roland-berger-to-help-advance-its-ai-ambitions | O38: Verified
A39: Lebanon | B39: Policy | C39: Sectoral AI Strategy | D39: Government | E39: Policy | F39: National AI Strategy in Lebanese Industry (2020-2050) | G39: Ministry of Industry framework for integrating AI into Lebanon's industrial sector (R&D, smart production, competitiveness), building on the 2015 Integrated Vision for the Lebanese Industrial Sector. | H39: Strategic document | I39: 2020 | J39: 2026-08-09 | L39: Digital Watch Observatory | M39: Aggregator | N39: https://dig.watch/resource/national-artificial-intelligence-strategy-in-lebanese-industry-2020-2050 | O39: Verified
A40: Lebanon | B40: Policy | C40: National Strategy | D40: Government | E40: Policy | F40: ESCWA Advisory Report - AI Strategy for Lebanon | G40: UN ESCWA advisory report, requested by the then Ministry of State for Investment and Technology Affairs, diagnosing Lebanon's AI readiness (SWOT, prerequisites) and proposing vision, strategic goals and phased policy recommendations. | H40: Advisory report | I40: 2020 | J40: 2026-08-09 | L40: UN ESCWA | M40: Primary | N40: https://www.unescwa.org/sites/default/files/event/materials/advisory-report-development-artificial-intelligence-strategy-lebanon-en.pdf | O40: Verified
A41: Lebanon | B41: Policy | C41: Digital Government | D41: Government | E41: Policy | F41: OMSAR Digital Transformation Strategy (2020-2030) | G41: National digital transformation strategy approved in 2022 and led by the Office of the Minister of State for Administrative Reform, focused on e-government, digital identity and interoperability. | H41: Government strategy | I41: 2022 | J41: 2026-08-09 | L41: Levellers.ai (country review) | M41: Secondary | N41: https://www.levellers.ai/what-is/ai-regulation-lebanon | O41: Not yet verified | P41: Single secondary source; recommend confirming against OMSAR's own publication.
A42: Lebanon | B42: Policy | C42: Startup Funding Framework | D42: Government | E42: Policy | F42: BDL Circular 331 | G42: 2013 Banque du Liban scheme guaranteeing up to 75% of commercial banks' equity investments in knowledge-economy startups (~$400M envelope); the founding instrument of Lebanon's pre-crisis startup ecosystem, funding VCs and accelerators such as Berytech Fund II and Speed@BDD. | H42: Regulatory framework | I42: 2013 | J42: 2026-08-09 | L42: Wamda | M42: Primary (News) | N42: https://www.wamda.com/2017/05/lebanons-bdl-circular-birth-industry | O42: Verified | P42: Largely inactive since the 2019 financial crisis; kept for historical context on ecosystem financing.
A43: Lebanon | B43: General | C43: Incubation | D43: Cross-sector | E43: Hub | F43: Berytech | G43: Beirut innovation hub and incubator (originating from Universite Saint-Joseph) hosting and accelerating tech startups and managing venture funds for the Lebanese knowledge economy. | H43: Organization profile | I43: Not specified | J43: 2026-08-09 | L43: Company website (Berytech) | M43: Primary | N43: https://berytech.org/ | O43: Verified
A44: Lebanon | B44: General | C44: Venture Capital | D44: Finance | E44: Investor | F44: Berytech Fund II | G44: Circular 331-compliant venture fund launched in Feb 2015 with commitments of over $50M to invest in Lebanese knowledge-economy startups. | H44: Fund launch announcement | I44: 2015-02-25 | J44: 2026-08-09 | K44: $50,000,000 | L44: Company website (Berytech) | M44: Primary | N44: https://berytech.org/berytech-launches-berytech-fund-ii-to-support-the-lebanese-knowledge-economy/ | O44: Verified | P44: Funding figure is the fund's committed size, not a startup raise.
A45: Lebanon | B45: General | C45: Incubation | D45: Cross-sector | E45: Hub | F45: Speed@BDD | G45: Beirut seed accelerator launched after Circular 331; by 2018 it had accelerated 34 startups that created ~500 jobs, with follow-on funding and exits including GITEX Supernova winner Spike. | H45: Program overview | I45: 2015 | J45: 2026-08-09 | L45: Executive Magazine | M45: Primary (News) | N45: https://www.executive-magazine.com/entrepreneurship/lebanese-startups-in-need-of-investments | O45: Verified
A46: Lebanon | B46: General | C46: Incubation | D46: Cross-sector | E46: Hub | F46: Beirut Digital District (BDD) | G46: Beirut technology and innovation cluster hosting startups, accelerators (incl. Speed@BDD) and tech companies, forming the physical core of the Lebanese startup ecosystem. | H46: Organization profile | I46: Not specified | J46: 2026-08-09 | L46: Company website (BDD) | M46: Primary | N46: https://beirutdigitaldistrict.com/ | O46: Verified
A47: Lebanon | B47: General | C47: Venture Capital | D47: Finance | E47: Investor | F47: Middle East Venture Partners (MEVP) | G47: Beirut-founded venture capital firm investing in early and growth-stage tech across the Middle East, one of the region's largest VCs and a Circular 331-era anchor investor. | H47: Investor profile | I47: Not specified | J47: 2026-08-09 | L47: IncubatorList | M47: Aggregator | N47: https://incubatorlist.com/top-vcs-in-lebanon | O47: Not yet verified | P47: Well-known firm but sourced here only to an aggregator; confirm via mevp.com.
A48: Lebanon | B48: General | C48: Venture Capital | D48: Finance | E48: Investor | F48: B&Y Venture Partners | G48: Beirut-based venture capital fund ('Founders Backing Founders') investing in early-stage technology startups from Lebanon and the region. | H48: Investor profile | I48: Not specified | J48: 2026-08-09 | L48: IncubatorList | M48: Aggregator | N48: https://incubatorlist.com/top-vcs-in-lebanon | O48: Not yet verified
A49: Lebanon | B49: General | C49: Incubation | D49: Cross-sector | E49: Hub | F49: UK Lebanon Tech Hub | G49: Non-profit UK-Lebanon initiative supporting the growth of Lebanon's tech ecosystem by connecting startups with mentors, investors and international resources. | H49: Organization profile | I49: Not specified | J49: 2026-08-09 | L49: Startersss (accelerator directory) | M49: Aggregator | N49: https://www.startersss.com/accelerators-post/accelerator-beirut | O49: Not yet verified
A50: Lebanon | B50: General | C50: AI Community / Ecosystem | D50: Cross-sector | E50: Hub | F50: Beirut AI | G50: Lebanese non-profit (since 2017) and the country's largest applied-AI community: bootcamps, AI Weekend, hackathons and university workshops to make AI tools and knowledge accessible in Lebanon. | H50: Organization profile | I50: 2017 | J50: 2026-08-09 | L50: Beirut AI (official site) | M50: Primary | N50: https://beirutai.org/ | O50: Verified
A51: Lebanon | B51: Enterprise AI | C51: AI Education & Consulting | D51: Education | E51: Startup | F51: Zaka | G51: Beirut community-driven AI company (founded 2020) offering AI education programs (AI Bootcamp, SEEDS), corporate AI consulting and talent placement across MENA; Microsoft Global Training Partner with 110+ AI engineers graduated and 2,500+ upskilled. | H51: Company profile | I51: 2020 | J51: 2026-08-09 | L51: Company website (Zaka) | M51: Primary | N51: https://zaka.ai/ | O51: Verified
A52: Lebanon | B52: Enterprise AI | C52: Autonomous Robotics | D52: Industry | E52: Startup | F52: Revotonix | G52: Founded 2018 and described as the first startup in the Arab region developing fully autonomous mobile robots and mechatronics solutions; operates in Lebanon, UAE and Germany across hospitality, healthcare and intralogistics. | H52: Company profile | I52: 2018 | J52: 2026-08-09 | L52: Beirut AI (team profile) | M52: Secondary | N52: https://beirutai.org/meet-the-team-meetups/ | O52: Not yet verified | P52: Description drawn from a co-founder bio on Beirut AI's site; confirm against Revotonix's own materials.
A53: Lebanon | B53: Healthtech | C53: Surgical AI / AR | D53: Healthcare | E53: Startup | F53: Proximie | G53: Connected-surgery platform combining augmented reality, AI and ML to let surgeons virtually 'scrub in' to operating rooms worldwide; founded 2015-2016 by Lebanese surgeon Nadine Hachach-Haram, HQ London, ~$80M raised. | H53: Company profile | I53: 2016 | J53: 2026-08-09 | K53: $80,000,000 | L53: Arab News | M53: Primary (News) | N53: https://www.arabnews.com/node/2567746/amp | O53: Verified | P53: Lebanon-diaspora founded, HQ in London (same treatment as InstaDeep for Tunisia). Funding figure is cumulative, per Arab News.
A54: Lebanon | B54: Fintech | C54: AI Trading | D54: Finance | E54: Startup | F54: Neotic | G54: Lebanese fintech providing AI-driven trade ideas and backtesting tools for stock market decision-making. | H54: Company profile | I54: Not specified | J54: 2026-08-09 | L54: Nucamp (ecosystem guide) | M54: Aggregator | N54: https://www.nucamp.co/blog/coding-bootcamp-lebanon-lbn-government-the-complete-guide-to-using-ai-in-the-government-industry-in-lebanon-in-2025 | O54: Not yet verified | P54: SEO-grade source; confirm against neotic.ai before relying on details.
A55: Lebanon | B55: Fintech | C55: AI in Banking/Lending Software | D55: Finance | E55: Startup | F55: Bluering | G55: Beirut software company providing lending-automation and credit-decisioning platforms for banks, incorporating AI-based credit scoring. | H55: Company profile | I55: Not specified | J55: 2026-08-09 | L55: Nucamp (ecosystem guide) | M55: Aggregator | N55: https://www.nucamp.co/blog/coding-bootcamp-lebanon-lbn-government-the-complete-guide-to-using-ai-in-the-government-industry-in-lebanon-in-2025 | O55: Not yet verified
A56: Lebanon | B56: Agritech | C56: Autonomous Ag Robotics / CV | D56: Agriculture | E56: Startup | F56: LUXEED Robotics | G56: AUB-linked agritech startup building AI computer-vision systems for drones that distinguish weeds from crops in real time for targeted treatment; piloted with Lebanese vineyards and expanding to European organic farms. | H56: Company profile | I56: Not specified | J56: 2026-08-09 | K56: Undisclosed | L56: Nucamp (ecosystem guide) | M56: Aggregator | N56: https://www.nucamp.co/blog/coding-bootcamp-lebanon-lbn-lebanons-top-10-startups-that-tech-professionals-should-watch-out-for-in-2025 | O56: Not yet verified | P56: Source quotes ~LBP 15bn (~$1.5M) in grants/seed incl. Kafalat iSME; figure left Undisclosed pending a primary source.
A57: Lebanon | B57: Enterprise AI | C57: EdTech / Robotics | D57: Education | E57: Startup | F57: Cherpa | G57: Beirut edtech platform teaching robotics, coding and AI through project-based virtual missions, preparing students for technology careers. | H57: Company profile | I57: Not specified | J57: 2026-08-09 | L57: StartupBlink | M57: Aggregator | N57: https://www.startupblink.com/top-startups/beirut-lb | O57: Not yet verified
A58: Lebanon | B58: General | C58: Public Startup Financing | D58: Finance | E58: Investor | F58: Kafalat iSME | G58: State-backed equity co-investment and grant program for innovative Lebanese SMEs and startups; among the most active early-stage funders in the country (58 rounds per Tracxn). | H58: Investor profile | I58: Not specified | J58: 2026-08-09 | L58: Tracxn | M58: Aggregator | N58: https://tracxn.com/d/geographies/lebanon/__y_ABi6FaHH7l8ygqHM_jTAMLnK5mXJQ7pl-DyBmVN4M | O58: Not yet verified | P58: Confirm program status post-crisis via kafalat.com.lb.
A59: Lebanon | B59: Enterprise AI | C59: Music / Recommendation AI | D59: Industry | E59: Startup | F59: Anghami | G59: Music-streaming platform founded in Beirut in 2012, using ML-driven recommendation and personalization; first Arab tech company listed on Nasdaq (2021), HQ since relocated to Abu Dhabi. | H59: Company profile | I59: 2012 | J59: 2026-08-09 | L59: Tracxn | M59: Aggregator | N59: https://tracxn.com/d/geographies/lebanon/__y_ABi6FaHH7l8ygqHM_jTAMLnK5mXJQ7pl-DyBmVN4M | O59: Not yet verified | P59: Lebanon-founded, HQ relocated to UAE; AI is a feature layer rather than the core product - flagged for a scope decision.
A60: Morocco | B60: Agritech | C60: Soil Diagnostics | D60: Agriculture | E60: Startup | F60: Sand to Green | G60: Proprietary AI and satellite analysis (RegenWise) for monitoring arid soil restoration and carbon sequestration.using machine learning to solve the highly complex, unpredictable problem of desertification and soil degradation at a global scale | H60: Product specifications | I60: 2022 | J60: 2026-07-08 | K60: $1,000,000 | L60: Company website (Sand to Green) | M60: Primary | N60: https://sandtogreen.com/ | O60: Verified
A61: Morocco | B61: Healthtech | C61: Diagnostics | D61: Healthcare | E61: Startup | F61: DeepEcho | G61: Deep learning algorithms trained on fetal ultrasound videos to detect congenital malformations. | H61: Clinical trial validation | I61: 2025-11-10 | J61: 2026-07-08 | K61: Undisclosed | L61: Company website (DeepEcho) | M61: Primary | N61: https://deepecho.io/ | O61: Verified
A62: Morocco | B62: Policy | C62: National Strategy | D62: Government | E62: Policy | F62: Digital Morocco 2030 (National AI Synthesis) | G62: Synthesis report from Morocco's First National AI Conference (Rabat, July 1-2, 2025), establishing eight foundational strategic pillars (trust & governance, sovereign infrastructure, human capital, innovation & local AI production, financing & adoption, international cooperation, inclusion, concrete action) and recommendations toward a future comprehensive National AI Strategy. The report's own recommendations section calls for Morocco to "design a comprehensive roadmap for AI" as a next step - as of this report, a finalized, formally adopted national AI strategy does not yet exist; this conference establishes its foundational direction. | H62: Official strategic document | I62: 2025-09-01 | J62: 2026-07-18 00:00:00 | K62: $1,200,000,000 (UNCONFIRMED - see note) | L62: Ministry of Digital Transition (MMSP) | M62: Primary (Government) | N62: https://www.mmsp.gov.ma/sites/default/files/2025-09/Rapport%20de%20Synthe%CC%80se%20ANG.pdf | O62: Verified
A63: Morocco | B63: General | C63: Venture Capital | D63: Finance | E63: Investor | F63: UM6P Ventures | G63: early-stage investment arm of University Mohammed VI Polytechnic, backed by OCP Group, focusing on advancing scientific and tech-driven innovations in Africa through Digital Transformation and Deeptech funds. The firm supports startups in AgTech, GreenTech, HealthTech, and Industry and AI, offering capital, infrastructure, and programs like Plug and Play Morocco and U-Foundersh . | H63: Investment portfolio | I63: 2021-04-01 | J63: 2026-07-08 | K63: N/A | L63: Company website (UM6P Ventures) | M63: Primary | N63: https://um6pventures.com/ | O63: Verified
A64: Morocco | B64: General | C64: Incubation | D64: Cross-sector | E64: Hub | F64: Technopark Morocco | G64: National network of incubators hosting local AI innovators with centers in Casablanca, Rabat, Tangier and Agadir. | H64: Directory of incubators | I64: Not specified | J64: 2026-07-08 | K64: N/A | L64: Company website (Technopark) | M64: Primary | N64: https://www.technopark.ma/ | O64: Verified
A65: Morocco | B65: Agritech | C65: Remote Sensing | D65: Agriculture | E65: Startup | F65: SOWIT | G65: Combining satellite remote sensing and soil sensors with agronomic AI models to optimize irrigation. | H65: Product specifications | I65: 2026-05-24 | J65: 2026-07-08 | K65: Undisclosed | L65: Company website (SOWIT) | M65: Primary | N65: https://sowit.co/ | O65: Verified
A66: Morocco | B66: Enterprise AI | C66: Logistics & Retail | D66: Industry | E66: Startup | F66: KubicBits | G66: SaaS platform (KubicFleet) and AI-driven autonomous multi-agent architecture solutions for the management of logistics fleets. | H66: Company Profile | I66: Not specified | J66: 2026-07-08 | K66: Undisclosed | L66: Start-up website | M66: Aggregator | N66: https://www.start-up.ma/liste-startups-au-maroc/kubicbits/ | O66: Verified
A67: Morocco | B67: Enterprise AI | C67: IoT Infrastructure | D67: Industry | E67: Startup | F67: ABA Technology | G67: Artificial intelligence infrastructures applied to the Internet of Things (IoT) for connecting and analyzing data in smart cities. | H67: Ecosystem Profile | I67: 2026-04-01 | J67: 2026-07-08 | K67: Undisclosed | L67: Company website (ABA Technology) | M67: Primary | N67: https://aba.technology/ | O67: Verified
A68: Morocco | B68: General | C68: Incubation | D68: Cross-sector | E68: Hub | F68: Rally AI Future Lab (Jazari Institute) | G68: Intensive program and innovation lab deployed in Merzouga aimed at training local talent to develop "Made in Morocco" AI solutions. | H68: News article | I68: 2026-06-16 | J68: 2026-07-08 | K68: N/A | L68: Africa AI News | M68: Primary (News) | N68: https://www.africaainews.com/p/morocco-launches-rally-ai-future | O68: Verified
A69: Morocco | B69: Policy | C69: National Strategy | D69: Government | E69: Policy | F69: AL-KHAWARIZMI R&D Program | G69: Government program allocating 50 million dirhams to encourage applied scientific research in AI and its applications. | H69: Government Policy Document | I69: 2020 | J69: 2026-07-10 | K69: N/A | L69: Agence de developpement digital (ADD) | M69: Primary (Government) | N69: https://www.add.gov.ma/programme-al-khawarizmi | O69: Verified
A70: Morocco | B70: General | C70: Academic Infrastructure | D70: Education | E70: Hub | F70: School of AI in Fes (EIDIA) | G70: Academic institution established to advance AI education, training, and human capital development. | H70: Ecosystem Profile | I70: 2019 | J70: 2026-07-10 | K70: N/A | L70: Jeune Afrique | M70: Primary (News) | N70: https://www.jeuneafrique.com/emploi-formation/810532/maroc-une-nouvelle-ecole-dintelligence-artificielle-a-fes/ | O70: Verified
A71: Morocco | B71: General | C71: Academic Infrastructure | D71: Education | E71: Hub | F71: AI Movement (UM6P) | G71: Academic and research center aiming to strategically position Morocco as a regional hub for impactful AI. | H71: Ecosystem Profile | I71: 2021 | J71: 2026-07-10 | K71: N/A | L71: Cambridge University Press (Data & Policy journal) | M71: Secondary (Academic Survey) | N71: https://www.cambridge.org/core/journals/data-and-policy/article/exploring-ai-governance-in-the-middle-east-and-north-africa-mena-region-gaps-efforts-and-initiatives/867858AA465EEB06B5C43FF7048D8652 | O71: Verified
... A73: Morocco | B73: General | C73: Venture Capital | D73: Finance | E73: Investor | F73: Flat6Labs Morocco (with Tamwilcom) | G73: MENA seed/early-stage VC firm's first Morocco expansion, an accelerator targeting AgriTech, FinTech, GreenTech, AI and digital health startups, run with public financial institution Tamwilcom. | H73: News article | I73: 2025-04-28 | J73: 2026-07-10 | K73: N/A | L73: Tech In Africa | M73: Primary (News) | N73: https://www.techinafrica.com/flat6labs-and-tamwilcom-launch-accelerator-to-fuel-moroccos-tech-startup-ecosystem/ | O73: Verified
A74: Tunisia | B74: Enterprise AI | C74: Decision-Support | D74: Industry | E74: Startup | F74: InstaDeep | G74: Scalable AI decision support systems using deep reinforcement learning to optimize logistics and biotechnology. | H74: Company presentation | I74: 2023-01-25 | J74: 2026-07-27 | K74: $100,000,000 | L74: Company website (InstaDeep) | M74: Primary | N74: https://www.instadeep.com/ | O74: Verified | P74: Re-confirmed via dedicated research pass: Tunisia-founded (2014), HQ London, BioNTech acquisition ~$684M (Bloomberg).
A75: Tunisia | B75: Enterprise AI | C75: SaaS | D75: Industry | E75: Startup | F75: Cynoia | G75: AI-powered unified workspace software that consolidates communications and project tracking algorithms. | H75: SaaS Specifications | I75: Not specified | J75: 2026-07-08 | K75: $930,000 | L75: Company website (Cynoia) | M75: Primary | N75: https://cynoia.com/ | O75: Verified
A76: Tunisia | B76: General | C76: Venture Capital | D76: Finance | E76: Investor | F76: 216 Capital | G76: Venture capital firm (pre-seed and seed) focused on supporting tech and AI entrepreneurs in Southern Europe and Africa. | H76: Fund settings | I76: Not specified | J76: 2026-07-08 | K76: $1,000,000 | L76: Company website (216 Capital) | M76: Primary | N76: https://216capital.vc/ | O76: Verified
A77: Tunisia | B77: Policy | C77: Legal Frameworks | D77: Government | E77: Policy | F77: Tunisia Startup Act (Smart Capital) | G77: State-backed legal framework offering license exemptions and tax incentives for certified innovators. | H77: Regulatory law text | I77: 2018-04-01 | J77: 2026-07-08 | K77: N/A | L77: Smart Capital (Tunisia Startup Act portal) | M77: Primary (Government) | N77: https://startup.smartcapital.tn/ | O77: Verified
A78: Tunisia | B78: Enterprise AI | C78: NLP | D78: Industry | E78: Startup | F78: iCompass | G78: Natural language processing modules and TunBERT models for the analysis of low-resource Arabic dialects. | H78: SaaS Product Profile | I78: 2021-11-17 | J78: 2026-07-22 | K78: Undisclosed | L78: InstaDeep (official announcement) / Disrupt Africa | M78: Primary (News) | N78: https://instadeep.com/2021/06/instadeep-and-icompass-open-source-world-first-tunisian-dialect-ai-language-model-to-encourage-innovation/ | O78: Verified | P78: Verified: iCompass (founded 2019, Tunis; Hatem Haddad & Ahmed Nouisser) built TunBERT with InstaDeep - the first NLP language model for Tunisian dialect - open-sourced June 2021 (GitHub iCompass-ai/TunBERT). Source upgraded from euroquity to InstaDeep's official announcement.
A79: Tunisia | B79: Enterprise AI | C79: Autonomous Robotics | D79: Industry | E79: Startup | F79: Enova Robotics | G79: Manufacturing and design of robust autonomous security robots (PGuard) and open-source MiniLab research platforms. | H79: Funding history | I79: 2018-09-17 | J79: 2026-07-27 | K79: $1,600,000 | L79: MenaBytes | M79: Primary (News) | N79: https://www.menabytes.com/enova-robotics-1-6-million/ | O79: Verified | P79: Confirmed via dedicated research pass: Sousse robotics firm (founded 2014), AI genuinely embedded (facial recognition, autonomy) in PGUARD security robot.
A80: Tunisia | B80: Policy | C80: National Strategy | D80: Government | E80: Policy | F80: Tunisia AI Roadmap | G80: National strategic roadmap setting out key objectives and action plans for ethical and localized AI development. | H80: OECD Index | I80: 2021 | J80: 2026-07-08 | K80: N/A | L80: AIWorld.eu (Country Profile) | M80: Aggregator | N80: https://aiworld.eu/geo/tunisia | O80: Verified
A81: Tunisia | B81: Enterprise AI | C81: SaaS Marketing | D81: Industry | E81: Startup | F81: Easy Ads | G81: AI-powered digital advertising optimization engines designed to help SMEs deploy targeted campaigns. | H81: News summaries | I81: Not specified | J81: 2026-07-08 | K81: Undisclosed | L81: AIWorld.eu (Country Profile) | M81: Aggregator | N81: https://aiworld.eu/geo/tunisia | O81: Verified
A82: Tunisia | B82: General | C82: Academic Infrastructure | D82: Education | E82: Hub | F82: INSAT | G82: A top-level technical university anchoring scientific research, engineering training and AI incubation programs. | H82: Academic framework | I82: 2025 | J82: 2026-07-08 | K82: N/A | L82: AIWorld.eu (Country Profile) | M82: Aggregator | N82: https://aiworld.eu/geo/tunisia | O82: Verified
A83: Tunisia | B83: General | C83: Academic Infrastructure | D83: Education | E83: Hub | F83: Pristini School of AI | G83: First university to specialize entirely in Artificial Intelligence education in Tunisia and Africa. | H83: Academic framework | I83: 2023 | J83: 2026-07-10 | K83: N/A | L83: Pristini AI University (official site) | M83: Primary | N83: https://www.pristiniaiuniversity.tn/fr | O83: Verified
A84: Tunisia | B84: Agritech | C84: Standards Framework | D84: Agriculture | E84: Policy | F84: AGRIVET SMART | G84: Standards framework finalized by the National Council of the Order of Veterinarians providing guidelines for AI in Agrifood. | H84: Regulatory framework | I84: 2023 | J84: 2026-07-10 | K84: N/A | L84: Cambridge University Press (Data & Policy journal) | M84: Secondary (Academic Survey) | N84: https://www.cambridge.org/core/journals/data-and-policy/article/exploring-ai-governance-in-the-middle-east-and-north-africa-mena-region-gaps-efforts-and-initiatives/867858AA465EEB06B5C43FF7048D8652 | O84: Verified
A85: Morocco | B85: General | C85: AI Data Center / Infrastructure | D85: Cross-sector | E85: Hub | F85: Nexus Core Systems AI Factory | G85: US firm Nexus Core Systems signed a $1.28bn MoU with Moroccan authorities at GITEX Africa 2026 to build a renewable-powered 'AI Factory' (HPC data centre, phase-1 ~16-40MW in Nouaceur, scaling toward 500MW) with Nvidia (Blackwell GB200), Naver and Lloyd Capital. | H85: Investment / MoU announcement | I85: 2026-04 | J85: 2026-07-22 | K85: $1,280,000,000 | L85: Ecofin Agency (corroborated by Developing Telecoms, MoroccoWorldNews) | M85: Primary (News) | N85: https://www.ecofinagency.com/news/1304-54600-morocco-signs-1-28-billion-mou-to-build-ai-factory | O85: Verified
A86: Morocco | B86: Enterprise AI | C86: NLP / Customer Experience | D86: Industry | E86: Startup | F86: ToumAI Analytics | G86: Startup (founded 2021) building NLP that analyses African and Arabic dialects to improve customer experience; raised $1M pre-seed (Feb 2025) led by Launch Africa Ventures. | H86: Funding announcement | I86: 2025-02 | J86: 2026-07-22 | K86: $1,000,000 | L86: LaunchBase Africa | M86: Primary (News) | N86: https://launchbaseafrica.com/2025/02/10/moroccan-ai-spin-off-toumai-secures-1-million-in-pre-seed-funding/ | O86: Verified
A87: Morocco | B87: Enterprise AI | C87: Autonomous Drones / Computer Vision | D87: Maritime | E87: Startup | F87: ATLAN Space | G87: Rabat startup (founded 2016) using AI for fully autonomous UAV/drone missions in environmental and marine monitoring; raised $1.1M Series A (Nov 2020) led by Maroc Numeric Fund II. | H87: Funding announcement | I87: 2020-11 | J87: 2026-07-22 | K87: $1,100,000 | L87: Disrupt Africa | M87: Primary (News) | N87: https://disruptafrica.com/2020/11/05/moroccan-startup-atlan-space-raises-1-1m-series-a-round/ | O87: Verified
A88: Morocco | B88: Healthtech | C88: AI Diagnostics / Digital Pathology | D88: Healthcare | E88: Startup | F88: DataPathology | G88: Founded 2020; uses AI and digital pathology for faster, more accurate cancer diagnosis (incl. cervical cancer) in underserved regions; raised $1M from Azur Innovation Fund (2023). | H88: Funding announcement | I88: 2023-05 | J88: 2026-07-22 | K88: $1,000,000 | L88: Wamda | M88: Primary (News) | N88: https://www.wamda.com/2023/05/moroccan-healthtech-datapathology-raises-1-million-azur-innovation-fund | O88: Verified
A89: Morocco | B89: Fintech | C89: eKYC / Identity | D89: Finance | E89: Startup | F89: Indatacore | G89: Casablanca startup (founded 2016) providing deep-learning eKYC (face matching, liveness detection, document analysis) for financial institutions. | H89: Company profile | I89: 2016 | J89: 2026-07-26 | K89: Undisclosed | L89: Lucidity Insights | M89: Aggregator | N89: https://lucidityinsights.com/startups/indatacore-18054 | O89: Verified | P89: Confirmed via dedicated research pass: real Casablanca eKYC/facial-recognition AI company, founded 2016.
A90: Morocco | B90: Enterprise AI | C90: Insurtech / Computer Vision | D90: Finance | E90: Startup | F90: SYGMA.AI | G90: Moroccan startup offering an AI/ML solution that detects vehicle damage and estimates repair cost from a single photo. | H90: Company profile | I90: Not specified | J90: 2026-07-26 | K90: Undisclosed | L90: Atlas Magazine | M90: Secondary | N90: https://www.atlas-mag.net/en/category/pays/maroc/sygma-ai-to-assess-motor-vehicle-damage-using-photos | O90: Verified | P90: Confirmed via dedicated research pass. Note: multiple unrelated 'Sygma' entities exist - confirmed this refers to the Moroccan car-damage-assessment AI company.
A91: Morocco | B91: Policy | C91: National AI Strategy | D91: Government | E91: Policy | F91: Maroc IA 2030 (AI Made in Morocco) | G91: National AI strategy led by the Ministry of Digital Transition, targeting a MAD 100bn GDP contribution, 50,000 AI jobs and 200,000 people trained by 2030, with a Jazari Institutes network, National Data Factory and sovereign cloud. | H91: Government strategy | I91: 2025 | J91: 2026-07-22 | K91: N/A | L91: Middle East AI News | M91: Primary (News) | N91: https://www.middleeastainews.com/p/new-ai-made-in-morocco-strategy | O91: Verified
A92: Morocco | B92: General | C92: AI Community / Ecosystem | D92: Cross-sector | E92: Hub | F92: MoroccoAI (Moroccan AI Society) | G92: Professional AI community focused on education, research and innovation; organises the annual MoroccoAI conference and meetups. | H92: Organization profile | I92: Not specified | J92: 2026-07-22 | K92: N/A | L92: MoroccoAI | M92: Primary | N92: https://morocco.ai/ | O92: Verified
A93: Morocco | B93: General | C93: Tech / AI Trade Show | D93: Cross-sector | E93: Hub | F93: GITEX Africa (Marrakech) | G93: Africa's largest tech and startup trade show, held annually in Marrakech under royal patronage; AI and digital infrastructure were headline themes at the 2025 and 2026 editions. | H93: Event | I93: 2025-04 | J93: 2026-07-22 | K93: N/A | L93: TechAfrica News | M93: Primary (News) | N93: https://techafricanews.com/2025/03/18/gitex-africa-morocco-2025-africas-tech-powerhouse-returns-bigger-than-ever/ | O93: Verified
A94: Morocco | B94: General | C94: Startup Accelerator | D94: Cross-sector | E94: Hub | F94: Plug and Play Morocco | G94: Casablanca accelerator (est. 2024) offering equity-free grants up to $50,000 to founders in sectors including AI, healthtech and smart cities. | H94: Organization profile | I94: 2024 | J94: 2026-07-22 | K94: N/A | L94: Plug and Play Tech Center | M94: Primary | N94: https://www.plugandplaytechcenter.com/locations/casablanca/morocco-accelerator | O94: Verified
A95: Morocco | B95: General | C95: AI/ML Event | D95: Cross-sector | E95: Hub | F95: Deep Learning IndabaX Morocco | G95: Moroccan national chapter of the Deep Learning Indaba, running annual machine-learning / deep-learning conferences and workshops. | H95: Event | I95: Not specified | J95: 2026-07-26 | K95: N/A | L95: IndabaX Morocco | M95: Primary | N95: https://indabaxmorocco.github.io/ | O95: Verified | P95: Confirmed via dedicated research pass: real event under the pan-African Deep Learning Indaba.
A96: Morocco | B96: General | C96: Venture Capital | D96: Finance | E96: Investor | F96: Azur Innovation Fund | G96: Casablanca-based VC investing in high-impact tech; led the $1M round into AI healthtech startup DataPathology. | H96: Investor profile | I96: 2023 | J96: 2026-07-22 | K96: N/A | L96: Wamda | M96: Primary (News) | N96: https://www.wamda.com/2023/05/moroccan-healthtech-datapathology-raises-1-million-azur-innovation-fund | O96: Verified
A97: Morocco | B97: General | C97: Venture Capital | D97: Finance | E97: Investor | F97: Maroc Numeric Fund II (MNF Ventures) | G97: Moroccan VC (MNF Ventures, formerly MITC Capital) backing seed/Series A tech; led ATLAN Space's AI Series A round. | H97: Investor profile | I97: 2020 | J97: 2026-07-22 | K97: N/A | L97: Disrupt Africa | M97: Primary (News) | N97: https://disruptafrica.com/2020/11/05/moroccan-startup-atlan-space-raises-1-1m-series-a-round/ | O97: Verified
A98: Egypt | B98: Healthtech | C98: AI Pharmacy / e-Health | D98: Healthcare | E98: Startup | F98: Chefaa | G98: Founded 2017; AI-powered chronic-medication and pharmacy-delivery platform matching patients to pharmacies. | H98: Company profile | I98: 2017 | J98: 2026-07-22 | K98: Undisclosed | L98: The Startup Scene ME | M98: Primary (News) | N98: https://thestartupscene.me/INVESTMENTS/Egyptian-Healthtech-Chefaa-Raises-Undisclosed-Venture-Round | O98: Verified
A99: Egypt | B99: Fintech | C99: Embedded / Revenue-Based Financing | D99: Finance | E99: Startup | F99: FlapKap | G99: Egypt-born fintech providing revenue-based and embedded financing to SMEs using AI credit models built on open-banking and alternative data; raised $34M pre-Series A (2024). | H99: Funding announcement | I99: 2024-09 | J99: 2026-07-22 | K99: $34,000,000 | L99: Wamda | M99: Primary (News) | N99: https://www.wamda.com/2024/09/flapkap-secures-34-million-pre-series-a-mix-debt-equity | O99: Verified
A100: Egypt | B100: Enterprise AI | C100: Arabic Speech AI / NLP | D100: Industry | E100: Startup | F100: Intella | G100: Egyptian-founded (2021) dialectal-Arabic speech-AI company; transcription/analytics across 25+ Arabic dialects; raised $12.5M Series A (2025). | H100: Funding announcement | I100: 2025 | J100: 2026-07-22 | K100: $12,500,000 | L100: MENAbytes | M100: Primary (News) | N100: https://www.menabytes.com/intella-series-a/ | O100: Verified
A101: Egypt | B101: Enterprise AI | C101: Arabic AI Agents / Automation | D101: Industry | E101: Startup | F101: Nanovate | G101: Cairo AI startup (founded 2025) building Arabic-language AI tools - chat and voice agents, CRM/ERP integrations and no-code deployment; raised $2M pre-seed. | H101: Funding announcement | I101: 2025 | J101: 2026-07-22 | K101: $2,000,000 | L101: Disrupt Africa | M101: Primary (News) | N101: https://disruptafrica.com/2025/11/21/how-egypts-nanovate-is-using-ai-to-help-mena-businesses-work-smarter-in-their-own-language/ | O101: Verified
...

Sheet Summary
A1: Metric | B1: Count
A2: Total entities | B2: =COUNTA(Dataset!A2:A377) -> 376
A4: By Verification Status
A5: Mismatch found | B5: =COUNTIF(Dataset!O2:O377,"Mismatch found") -> 0
A6: Not yet verified | B6: =COUNTIF(Dataset!O2:O377,"Not yet verified") -> 39
A7: Verified | B7: =COUNTIF(Dataset!O2:O377,"Verified") -> 337
A9: By Country
A10: Algeria | B10: =COUNTIF(Dataset!A2:A377,"Algeria") -> 65
A11: Egypt | B11: =COUNTIF(Dataset!A2:A377,"Egypt") -> 113
A12: Lebanon | B12: =COUNTIF(Dataset!A2:A377,"Lebanon") -> 24
A13: Morocco | B13: =COUNTIF(Dataset!A2:A377,"Morocco") -> 89
A14: Tunisia | B14: =COUNTIF(Dataset!A2:A377,"Tunisia") -> 85
A16: By Entity Type
A17: Hub | B17: =COUNTIF(Dataset!E2:E377,"Hub") -> 156
A18: Investor | B18: =COUNTIF(Dataset!E2:E377,"Investor") -> 30
A19: Policy | B19: =COUNTIF(Dataset!E2:E377,"Policy") -> 55
A20: Startup | B20: =COUNTIF(Dataset!E2:E377,"Startup") -> 135
A22: By Application Sector
A23: Agriculture | B23: =COUNTIF(Dataset!D2:D377,"Agriculture") -> 20
A24: Cross-sector | B24: =COUNTIF(Dataset!D2:D377,"Cross-sector") -> 62
A25: Education | B25: =COUNTIF(Dataset!D2:D377,"Education") -> 76
A26: Energy | B26: =COUNTIF(Dataset!D2:D377,"Energy") -> 4
A27: Finance | B27: =COUNTIF(Dataset!D2:D377,"Finance") -> 60
A28: Government | B28: =COUNTIF(Dataset!D2:D377,"Government") -> 44
A29: Healthcare | B29: =COUNTIF(Dataset!D2:D377,"Healthcare") -> 16
A30: Industry | B30: =COUNTIF(Dataset!D2:D377,"Industry") -> 93
A31: Maritime | B31: =COUNTIF(Dataset!D2:D377,"Maritime") -> 1

Sheet Change Log
A1: Fix | B1: Detail
A2: v1 -> v2: schema redesign | B2: Split ambiguous 'Date' column into Reference Date and Last Verified; added Source Name, Source Type, Verification Status fields; standardized N/A vs Undisclosed vs Not specified conventions.
A3: v2 -> v3: verification pass | B3: Fetched and confirmed 8 Cambridge-cited claims; corrected Libyan Spider (AI website builder, not 'hosting nodes') and University of Tripoli (general A-Hub accelerator, not AI-specific 'hackathons') after both were found unsupported by their original sources; fixed Source Type inconsistencies (Crunchbase rows standardized to Aggregator).
A4: v3 -> v4: user re-verification pass | B4: User independently re-verified the majority of entities against new/better sources (Verified count: 15 -> 61 of 69). Added Libya, Morocco, Algeria, Tunisia entries with richer, specifically-sourced descriptions.
A5: v4 -> v5 (this version): final QA pass | B5: Normalized Verification Status casing throughout (lowercase 'verified' / typo 'verfied' -> 'Verified'); standardized all funding figures to consistent $X,XXX,XXX format; fixed LinkedIn source-name capitalization (6 rows) and one 'aba techonlogy' typo; converted remaining DD/MM/YYYY dates to ISO format.
A6: Games Kings (Libya) - REVERTED, not accepted | B6: Cited source (King.com press release) fetched and confirmed to be entirely unrelated - covers a 2022 acquisition of a Swedish AI company by the Candy Crush developer. Reverted to 'Mismatch found' and the original Crunchbase source pending real re-verification.
A7: The AI Campus (New Cairo) - confirmed and corrected | B7: Source fetched and confirmed genuinely accurate (official Orange Egypt press release). Description had a paste-related formatting error (rewritten); reference date corrected to 2026-04-20 (the article's own dateline, previously recorded as an unmatched '06/04/2026'); properly credits both real partners (Paragon | Adeer and Plug and Play).
A8: Digital Morocco 2030 - flagged, not accepted as Verified | B8: A new $1.2 billion funding figure was added with no supporting note. Reverted to 'Not yet verified' pending a direct check against the source PDF.
A9: AgriCan - flagged, not accepted as Verified | B9: Description text reads as generic pan-African commentary that doesn't clearly match this specific Egyptian company. Reverted to 'Not yet verified' pending confirmation.
A10: SCTPAI/LibiGPT - flagged, not accepted as Verified | B10: A new, more specific claim was added alongside a new source URL. Reverted to 'Not yet verified' pending confirmation this exact claim is supported.
A11: v5 -> v6: verification + expansion pass | B11: Verified the 5 pending rows: Algeria Startup Act, Synapse Analytics (Konan; $2M/2024; founders) and iCompass (TunBERT; source upgraded to InstaDeep) confirmed and set to Verified; Games Kings kept 'Mismatch found' (gameskings.ai has no verifiable Libya link) and Ytech kept 'Not yet verified' (no working/independent source). Added 55 new source-verified AI-ecosystem entities across all 5 countries (startups, hubs, VCs, universities, research labs, national strategies). New rows sourced only to a single secondary/aggregator source and not independently re-fetched were left 'Not yet verified' (no green fill) for a human check; the rest were confirmed against primary/known sources. Summary counts rebuilt from the data.
A12: v6 -> v7: large expansion pass | B12: Added 109 further source-verified AI-ecosystem entities across all 5 countries (AI startups, university labs/faculties, incubators/accelerators, VCs and public funds, national data centers/supercomputers, AI strategies and government programs). High-confidence entities (primary/official/reputable-press sources) set to 'Verified'; entities resting on a single aggregator/listicle/ResearchGate source were left 'Not yet verified' (no green fill) for a human check. Duplicates against existing rows were skipped. Summary rebuilt.
... A23: v10 -> v11: Libya removed, Lebanon added, Application Sector column added | B23: Removed all 33 Libya rows (out of project scope; target country is Lebanon). Added 24 Lebanon rows covering national AI/digital strategies (MITAI 2025-2030, ESCWA advisory, Industry AI 2020-2050, BDL Circular 331), ecosystem hubs (Berytech, BDD, Speed@BDD, UK Lebanon Tech Hub, Beirut AI), investors (Berytech Fund II, MEVP, B&Y, Kafalat iSME) and startups (Zaka, Proximie, Revotonix, Neotic, Bluering, LUXEED, Cherpa, Anghami). Rows resting on a single aggregator/SEO source left 'Not yet verified' (no green fill) for a human check. Added new 'Application Sector' column (D) classifying every row into: Education, Healthcare, Agriculture, Energy, Industry, Maritime + 3 added categories (Finance, Government, Cross-sector); Industry doubles as the catch-all for tech products (robotics, NLP, logistics, SaaS...) per user instruction. Summary rebuilt with live COUNTIF formulas incl. Application Sector breakdown.
