Workbook

Sheet Dataset
A1: Country | B1: Sector | C1: Sub-Sector | D1: Entity Type | E1: Maturity | F1: Entity / Innovation Name | G1: Key Innovation / Description | H1: Information Type | I1: Reference Date | J1: Last Verified | K1: Recent Funding | L1: Source Name | M1: Source Type | N1: Source URL | O1: Verification Status | P1: Notes
A2: Algeria | B2: Industry | C2: Developer & AI community | D2: Community/Association | E2: Established | F2: GDG Algiers (Google Developer Group Algiers & DevFest Algiers) | G2: Long-running Google Developer Group chapter in Algiers running DevFest Algiers and AI-focused programming ('Build with AI', AiFest at ENSIA via GDG on Campus), one of Algeria's largest volunteer tech communities training students in ML and cloud technologies. | H2: Community profile | I2: 2024 | J2: 2026-08-05 | L2: Google Developer Groups | M2: Primary | N2: https://gdg.community.dev/gdg-algiers/ | O2: Verified | P2: Official Google community platform page plus gdgalgiers.com DevFest 2024 site and GDG-on-Campus ENSIA AI event listings. [Added 2026-08-05 expansion pass]
A3: Algeria | B3: Education | C3: Machine learning community conference | D3: Community/Association | E3: Established | F3: IndabaX Algeria | G3: Algerian chapter of the Deep Learning Indaba movement 'Strengthening African Machine Learning', holding locally organized IndabaX Algeria editions (2022, 2023 and a listed 2025 edition) that gather students and researchers for ML/AI tutorials and talks. | H3: Event | I3: 2025 | J3: 2026-08-05 | L3: Deep Learning Indaba | M3: Primary | N3: https://deeplearningindaba.com/2025/indabax/algeria/ | O3: Verified | P3: Listed on the official Deep Learning Indaba site (2023 and 2025 IndabaX pages) plus dedicated indabaxalgeria.com site; 2025 page has limited detail. [Added 2026-08-05 expansion pass] [Merge re-audit 2026-08] Ecosystem Type corrected: 'Conference/Summit' -> 'Community/Association'. Was Conference/Summit - same pattern as IndabaX Tunisia: a recurring local chapter of the Deep Learning Indaba movement gathering students/researchers, not a single conference.
A4: Algeria | B4: Industry | C4: AI Skills Training | D4: Community/Association | E4: Established | F4: Skills Centers (Scale Centers) network | G4: Government network of seven free regional digital-skills centres (Algiers, Oran, Annaba, Setif, Chlef, Saida, Adrar) training youth in AI, IoT, cybersecurity and cloud. | H4: News article | I4: 2025 | J4: 2026-07-22 | L4: We Are Tech Africa | M4: Primary (News) | N4: https://www.wearetech.africa/en/fils-uk/news/public-management/algeria-launches-setif-skills-center-to-boost-youth-innovation-with-free-ai-and-ict-training | O4: Verified | P4: Corroborated by TechAfrica News. [Reclassified 2026-08-01] Old Sector: 'General' -> New: 'Energy, Agriculture, Maritime, Health, Industry, Education'. Old Entity Type: 'Hub' -> New Ecosystem Type: 'Community/Association'. [Refined 2026-08-02] Sector forced to single label 'Industry' (was multi-sector: Energy, Agriculture, Maritime, Health, Industry, Education). Maturity inferred as 'Established' (structural-type).
A5: Algeria | B5: Industry | C5: Pan-African Startup & AI Conference | D5: Conference/Summit | E5: Established | F5: African Startup Conference (Algiers) | G5: Annual pan-African startup conference at CIC Algiers; 3rd edition (Dec 2024) put AI at its heart with 45 ministers, 800+ investors/startups, an AI tech exhibition and an African VC Summit. | H5: News article | I5: 2024-12 | J5: 2026-07-22 | L5: AL24 News | M5: Primary (News) | N5: https://al24news.dz/en/african-start-up-conference-ai-at-the-heart-of-3rd-edition-in-algiers/ | O5: Verified | P5: [Reclassified 2026-08-01] Old Sector: 'General' -> New: 'Energy, Agriculture, Maritime, Health, Industry, Education'. Old Entity Type: 'Hub' -> New Ecosystem Type: 'Conference/Summit'. [Refined 2026-08-02] Sector forced to single label 'Industry' (was multi-sector: Energy, Agriculture, Maritime, Health, Industry, Education). Maturity inferred as 'Established' (structural-type).
A6: Algeria | B6: Industry | C6: Tech Conference (AI/Cloud/Cyber) | D6: Conference/Summit | E6: Established | F6: Algeria 2.0 | G6: Long-running Algerian tech event (13th edition, 24-28 Nov 2026, Sidi Abdellah Cyberparc) with workshops and hackathons on AI, cloud, cybersecurity, web/mobile and SaaS. | H6: Event page | I6: 2026-11-24 | J6: 2026-07-22 | L6: Algeria 2.0 (official) | M6: Primary | N6: https://algeria20.com/?lang=en | O6: Verified | P6: [Reclassified 2026-08-01] Old Sector: 'General' -> New: 'Energy, Agriculture, Maritime, Health, Industry, Education'. Old Entity Type: 'Hub' -> New Ecosystem Type: 'Hackathons'. [Refined 2026-08-02] Sector forced to single label 'Industry' (was multi-sector: Energy, Agriculture, Maritime, Health, Industry, Education). Maturity inferred as 'Idea-stage' (hackathon-type). [Audit 2026-08-05] Entity Type corrected: 'Hackathons' -> 'Conference/Summit'. [Audit 2026-08-05] Reason: long-running tech conference (13th edition); hackathons are a sub-activity [Audit 2026-08-05] Maturity corrected: 'Idea-stage' -> 'Established'. [Audit 2026-08-05] Reason: 13th-edition long-running event; structural-type
A7: Algeria | B7: Health | C7: E-health innovation competition | D7: Conference/Summit | E7: Early | F7: Algiers Slush'D E-Health Innovation Awards (Roche Algérie x Algeria Venture) | G7: Inaugural Algiers Slush'D health-innovation track co-organized by Roche Algérie and public accelerator Algeria Venture under the patronage of the startups and health ministries; in January 2025 it selected three digital-health startups (Sihatech, Docteur 360, M-Click) from 40 submissions for a dedicated acceleration program. | H7: Event | I7: 2025-01-24 | J7: 2026-08-05 | L7: Algérie Eco | M7: Primary (News) | N7: https://algerie-eco.com/2025/01/24/e-sante-3-startups-algeriennes-recompensees-pour-leur-innovation/ | O7: Verified | P7: Algérie Eco report read directly; also relayed by AllAfrica, naming organizers, jury criteria and the three winners. [Added 2026-08-05 expansion pass]
A8: Algeria | B8: Industry | C8: Tech leadership forum (AI theme) | D8: Conference/Summit | E8: Established | F8: CTO Forum Algeria | G8: Technology leadership forum organized by BoostEvent whose inaugural edition (8-10 May 2023, CIC Abdelatif-Rahal, Algiers) took AI as its opening theme with ~150 exhibitors and speakers including Merouane Debbah on large language models and Algeria Venture's Sid Ali Zerrouki. | H8: Event | I8: 2023-05-08 | J8: 2026-08-05 | L8: Charikati | M8: Primary (News) | N8: https://dzcharikati.net/1e-cto-forum-algeria-lintelligence-artificielle-comme-thematique-inaugurale/ | O8: Verified | P8: Detailed Charikati event report read directly, listing organizers, ministers in attendance and AI program content. [Added 2026-08-05 expansion pass]
A9: Algeria | B9: Industry | C9: National ICT & AI forum | D9: Conference/Summit | E9: Established | F9: Connected Algeria 2025 | G9: Government ICT and digital transformation forum held 6-7 April 2025 at the International Conference Center in Algiers under the Ministry of Post and Telecommunications (Minister Sid Ali Zerrouki), gathering 1,000+ experts; AI was a central theme, with the minister announcing the national AI strategy was in its final drafting phase. | H9: Event | I9: 2025-04-06 | J9: 2026-08-05 | L9: Ouest Tribune | M9: Primary (News) | N9: https://ouest-tribune.dz/connected-algeria-2025-une-plateforme-strategique-pour-la-transformation-numerique-de-lalgerie/ | O9: Verified | P9: Cross-checked Ouest Tribune report with APS closing-session coverage and the official connectedalgeria.dz site. [Added 2026-08-05 expansion pass]
A10: Algeria | B10: Industry | C10: Venture Capital | D10: Funding | E10: Established | F10: Afiya Investments | G10: First venture-capital fund (FCPR) approved by Algeria's market regulator COSOB, managed by Tell Group, financing innovative early/growth-stage startups. | H10: News article | I10: 2025 | J10: 2026-07-27 | K10: Undisclosed | L10: Techpression | M10: Primary (News) | N10: https://techpression.com/algeria-startup-ecosystem-2025-reforms-driving-tech-innovation-and-growth/ | O10: Verified | P10: [Pending verification] AI-specific mandate general. Confirmed via dedicated research pass: Algeria's first COSOB-approved private VC vehicle (FCPR), managed by Tell Markets. Note: AI is not an explicit mandate - general VC vehicle. [Reclassified 2026-08-01] Old Sector: 'General' -> New: 'Energy, Agriculture, Maritime, Health, Industry, Education'. Old Entity Type: 'Investor' -> New Ecosystem Type: 'Funding'. [Refined 2026-08-02] Sector forced to single label 'Industry' (was multi-sector: Energy, Agriculture, Maritime, Health, Industry, Education). Maturity inferred as 'Established' (structural-type).
A11: Algeria | B11: Industry | C11: Venture Capital | D11: Funding | E11: Established | F11: Algerian Startup Fund (ASF) | G11: Public VC company (created Oct 2020 with six public banks) financing labelled Algerian startups, including AI ventures. | H11: Investor profile | I11: 2020-10 | J11: 2026-07-22 | L11: ASF (official) | M11: Primary | N11: https://asf.dz/ | O11: Verified | P11: Bank-backed fintech fund launch confirmed. [Reclassified 2026-08-01] Old Sector: 'Fintech' -> New: 'Energy, Agriculture, Maritime, Health, Industry, Education'. Old Entity Type: 'Investor' -> New Ecosystem Type: 'Funding'. [Refined 2026-08-02] Sector forced to single label 'Industry' (was multi-sector: Energy, Agriculture, Maritime, Health, Industry, Education). Maturity inferred as 'Established' (structural-type).
A12: Algeria | B12: Industry | C12: Public Venture Funding | D12: Funding | E12: Established | F12: Algerie Telecom AI/Cybersecurity/Robotics Fund | G12: State telecom operator's ~1.5bn-dinar (~$11M) fund announced 2025 to invest in AI, cybersecurity and robotics startups. | H12: News | I12: 2025-02 | J12: 2026-07-22 | K12: $11,000,000 | L12: LaunchBase Africa | M12: Primary (News) | N12: https://launchbaseafrica.com/2025/02/18/algeria-bets-big-on-ai-startups-with-new-investment-fund/ | O12: Verified | P12: [Reclassified 2026-08-01] Old Sector: 'General' -> New: 'Industry'. Old Entity Type: 'Investor' -> New Ecosystem Type: 'Funding'. [Refined 2026-08-02] Sector set to 'Industry'. Maturity inferred as 'Established' (structural-type).
A13: Algeria | B13: Industry | C13: Ecosystem Statistics | D13: Funding | E13: Established | F13: CEPS AI World Country Profile (Algeria) | G13: Macroeconomic tracking index compiling national parameters such as the $7 million in annual AI investments. | H13: Ecosystem statistics | I13: 2026-01-01 | J13: 2026-07-08 | K13: $7,000,000 | L13: AIWorld.eu (Country Profile) | M13: Aggregator | N13: https://www.aiworld.eu/geo/algeria | O13: Verified | P13: [Pending verification] Direct AI investments not individually verified. Confirmed via dedicated research pass: real Tunis asset manager; New Era Fund I (EUR7M first close) targets AI, biotech and green tech - AI is one of three sectors, not exclusive focus. [Reclassified 2026-08-01] Old Sector: 'General' -> New: 'Energy, Agriculture, Maritime, Health, Industry, Education'. Old Entity Type: 'Investor' -> New Ecosystem Type: 'Funding'. [Refined 2026-08-02] Sector forced to single label 'Industry' (was multi-sector: Energy, Agriculture, Maritime, Health, Industry, Education). Maturity inferred as 'Established' (structural-type).
A14: Algeria | B14: Industry | C14: Angel Investment Network | D14: Funding | E14: Established | F14: Casbah Business Angels | G14: First independent Algerian business-angel network (launched 2012 by Silicon Valley and Algerian CEOs), providing early-stage funding and mentorship to Algerian tech startups. | H14: Investor profile | I14: 2012 | J14: 2026-07-22 | L14: Gust | M14: Aggregator | N14: https://gust.com/organizations/casbah-business-angels | O14: Verified | P14: Cross-checked with VC4A and MAGNiTT; generalist tech investor. [Reclassified 2026-08-01] Old Sector: 'General' -> New: 'Energy, Agriculture, Maritime, Health, Industry, Education'. Old Entity Type: 'Investor' -> New Ecosystem Type: 'Funding'. [Refined 2026-08-02] Sector forced to single label 'Industry' (was multi-sector: Energy, Agriculture, Maritime, Health, Industry, Education). Maturity inferred as 'Established' (structural-type).
A15: Algeria | B15: Industry | C15: Public Venture Programme / Fund | D15: Funding | E15: Established | F15: National Venture Studio Programme | G15: $600M public-private, five-year programme (Algerian Startup Fund + CERIST + venture studio DeepMinds) to create 1,000+ tech ventures across all 58 provinces. | H15: News article | I15: 2025 | J15: 2026-07-22 | K15: $600,000,000 | L15: Middle East AI News | M15: Primary (News) | N15: https://www.middleeastainews.com/p/algeria-venture-studio-1000-startups | O15: Verified | P15: Cross-verified via DeepMinds press release and BridgeMENA. [Reclassified 2026-08-01] Old Sector: 'General' -> New: 'Energy, Agriculture, Maritime, Health, Industry, Education'. Old Entity Type: 'Investor' -> New Ecosystem Type: 'Funding'. [Refined 2026-08-02] Sector forced to single label 'Industry' (was multi-sector: Energy, Agriculture, Maritime, Health, Industry, Education). Maturity inferred as 'Established' (structural-type).
A16: Algeria | B16: Industry | C16: Startup Competition with AI Track | D16: Hackathons | E16: Idea-stage | F16: Algeria Startup Challenge (ASC) | G16: Largest Algerian open-innovation startup program (created 2018); 7th edition final (24 Nov 2025, Sidi Fredj) with 16 finalists and panels on AI's structuring role in the national economy. | H16: Event page + news | I16: 2025-11-24 | J16: 2026-07-22 | L16: Algeria Startup Challenge (official) | M16: Primary | N16: https://algeriastartupchallenge.com/ | O16: Verified | P16: Official site; venue and AI topics stated. [Reclassified 2026-08-01] Old Sector: 'General' -> New: 'Energy, Agriculture, Maritime, Health, Industry, Education'. Old Entity Type: 'Hub' -> New Ecosystem Type: 'Hackathons'. [Refined 2026-08-02] Sector forced to single label 'Industry' (was multi-sector: Energy, Agriculture, Maritime, Health, Industry, Education). Maturity inferred as 'Idea-stage' (hackathon-type).
A17: Algeria | B17: Industry | C17: Youth AI hackathon (health, energy, smart city themes) | D17: Hackathons | E17: Idea-stage | F17: Artificial Intelligence and Entrepreneurship Hackathon - Algeria 2026 (Sidi Abdellah) | G17: 38-hour national hackathon held 6-8 January 2026 at the Sidi Abdellah Scientific and Technological Hub, organized by 'Meeting of the Youth of Algeria' with the Ministry of Youth and Ministry of Higher Education; themes covered AI for youth mental health, smart waste/renewable-energy technologies and intelligent urban infrastructure. | H17: Event | I17: 2026-01-06 | J17: 2026-08-05 | L17: Université de Khenchela | M17: Primary | N17: https://www.univ-khenchela.dz/en/artificial-intelligence-and-entrepreneurship-hackathon-algeria-2026/ | O17: Verified | P17: Details taken from an official Algerian university announcement page including dates, themes and registration process. [Added 2026-08-05 expansion pass]
A18: Algeria | B18: Education | C18: National AI student competition | D18: Hackathons | E18: Idea-stage | F18: Concours National d'Intelligence Artificielle (Semaine nationale de l'IA 2025, Constantine) | G18: National AI competition launched 23 November 2025 at Université Frères Mentouri Constantine 1 during Algeria's National Week of AI and Scientific Research, gathering 60 innovative AI projects from students, teachers and researchers across the country. | H18: Event | I18: 2025-11-23 | J18: 2026-08-05 | L18: Algérie Presse Service (APS) | M18: Primary (Government) | N18: https://www.aps.dz/fr/algerie/education-et-technologie/mic0nq2g-lancement-d-un-concours-national-d-intelligence-artificielle-avec-la-participation-de-60-projets-innovants | O18: Verified | P18: Confirmed via APS (official state press agency) and corroborated by La Nouvelle République and Le Jour d'Algérie. [Added 2026-08-05 expansion pass]
A19: Algeria | B19: Industry | C19: AI-for-Good Competition | D19: Hackathons | E19: Idea-stage | F19: Djazairia Challenge 2025 - IA for Good | G19: AI-for-impact challenge positioning AI as a development lever for Africa, run with the Printemps numerique organisation. | H19: News article | I19: 2025 | J19: 2026-07-22 | L19: Printemps numerique | M19: Primary | N19: https://www.printempsnumerique.ca/ | O19: Verified | P19: [Pending verification] Run partly by a Canadian partner. [Reclassified 2026-08-01] Old Sector: 'General' -> New: 'Energy, Agriculture, Maritime, Health, Industry, Education'. Old Entity Type: 'Hub' -> New Ecosystem Type: 'Hackathons'. [Refined 2026-08-02] Sector forced to single label 'Industry' (was multi-sector: Energy, Agriculture, Maritime, Health, Industry, Education). Maturity inferred as 'Idea-stage' (hackathon-type). [Web re-verification 2026-08-05] Status 'Not yet verified' -> 'Verified'. Printemps numerique (the cited source org) published a dedicated article on 'Djazairia Challenge 2025 - IA for Good', confirming the AI-for-impact challenge and its framing of AI as a development lever for Africa. Confirming source: https://www.printempsnumerique.ca/nouvelles/article/djazairia-challenge-2025-ia-for-good-quand-lintelligence-artificielle-devient-un-levier-dimpact-pour-lafrique/
A20: Algeria | B20: Agriculture | C20: Agricultural AI hackathon | D20: Hackathons | E20: Idea-stage | F20: Défi de l'Agriculture Hackathon (ENSIA x ENSA) | G20: Three-day national hackathon (2nd edition, June 2025, Algiers) organized by the National Higher School of AI (ENSIA) and the National Higher School of Agronomy with the Jardin d'Essai du Hamma, Mobilis and AI Grid; 125 students in 25 teams built agricultural AI prototypes and produced a first-of-its-kind local dataset of 180,000+ plant images. | H20: Event | I20: 2025-06 | J20: 2026-08-05 | L20: AllAfrica (APS) | M20: Primary (News) | N20: https://fr.allafrica.com/stories/202506260675.html | O20: Verified | P20: APS state-agency report relayed by AllAfrica, including ENSIA director's 180,000-image dataset claim and minister Baddari's attendance. [Added 2026-08-05 expansion pass]
A21: Algeria | B21: Industry | C21: Corporate student tech/AI hackathon | D21: Hackathons | E21: Idea-stage | F21: Huawei Algérie Tech4Connect 2026 Hackathon | G21: First edition of Huawei Algeria's 'Tech4Connect' hackathon for university student teams; winning teams were awarded in March 2026, extending Huawei's ICT talent activities in Algeria beyond its ICT Academy and ICT Competition. | H21: Event | I21: 2026-03-12 | J21: 2026-08-05 | L21: L'Express DZ | M21: Primary (News) | N21: https://www.expressdz.dz/2026/03/12/huawei-algerie-recompense-les-equipes-etudiantes-laureates-du-premier-hackathon-tech4connect-2026/ | O21: Not yet verified | P21: Single national press report found (article page could not be fully fetched); headline confirms first-edition awards by Huawei Algérie in March 2026. [Added 2026-08-05 expansion pass]
A22: Algeria | B22: Industry | C22: Postal / fintech innovation hackathon | D22: Hackathons | E22: Idea-stage | F22: InnovPost Hackathon (Algérie Poste) | G22: First national hackathon of state postal operator Algérie Poste, launched in November 2024 to crowdsource technological innovation (digital payments and postal services) from students and young developers, with a first-edition prize ceremony recognizing winning teams. | H22: Event | I22: 2024-11-12 | J22: 2026-08-05 | L22: Algérie Poste | M22: Primary | N22: https://www.poste.dz/news/s/ceremonie-de-remise-des-prix-de-la-premiere-edition-de-lhackathon-innovpost-2024 | O22: Verified | P22: Official Algérie Poste press page for the INNOVPOST 2024 prize ceremony, corroborated by El Watan and Algérie Patriotique launch coverage (12 Nov 2024). [Added 2026-08-05 expansion pass]
A23: Algeria | B23: Industry | C23: Technology Park Operator & Incubation | D23: Incubator/Accelerator | E23: Established | F23: ANPT (Agence Nationale des Parcs Technologiques) | G23: State agency (est. 2004) operating the 92-ha Sidi Abdellah Technopark and regional technoparks; runs an incubator and the Virtual Incubation Program (VIP); hosts AI-focused events. | H23: Agency profile | I23: 2004 | J23: 2026-07-22 | L23: ANPT (official) | M23: Primary (Government) | N23: https://www.anpt.dz/about | O23: Verified | P23: Distinct from the Sidi Abdallah AI hubs (ANPT is the park operator). [Reclassified 2026-08-01] Old Sector: 'General' -> New: 'Energy, Agriculture, Maritime, Health, Industry, Education'. Old Entity Type: 'Hub' -> New Ecosystem Type: 'Incubator/Accelerator'. [Refined 2026-08-02] Sector forced to single label 'Industry' (was multi-sector: Energy, Agriculture, Maritime, Health, Industry, Education). Maturity inferred as 'Established' (structural-type).
A24: Algeria | B24: Industry | C24: State Accelerator & Fund | D24: Incubator/Accelerator | E24: Established | F24: Algeria Venture (A-Venture) | G24: First state-owned startup accelerator (est. Dec 2020) coaching and financing startups; agreement with SEAF created the $80M Algeria Innovation Funds; co-launched the AventureCloudz AI platform (2026). | H24: News article | I24: 2023-01 | J24: 2026-07-22 | K24: $80,000,000 (fund) | L24: Algerie Eco | M24: Primary (News) | N24: https://algerie-eco.com/2023/01/25/startups-algeria-venture-et-seaf-vont-creer-un-fonds-dinvestissement-dune-valeur-de-80-millions-de-dollars/ | O24: Verified | P24: Confirmed via dedicated research pass: real general entrepreneurship hub (Algiers, 2015) - not AI-specific, description should reflect that. Re-confirmed via dedicated research pass: Algeria's first private accelerator/coworking hub (2015) - correctly NOT categorized as an AI startup. [Reclassified 2026-08-01] Old Sector: 'General' -> New: 'Energy, Agriculture, Maritime, Health, Industry, Education'. Old Entity Type: 'Hub' -> New Ecosystem Type: 'Incubator/Accelerator'. [Refined 2026-08-02] Sector forced to single label 'Industry' (was multi-sector: Energy, Agriculture, Maritime, Health, Industry, Education). Maturity inferred as 'Established' (structural-type).
A25: Algeria | B25: Industry | C25: Venture Studio | D25: Incubator/Accelerator | E25: Established | F25: DeepMinds | G25: Decentralised venture studio and co-lead of Algeria's National Venture Studio Programme, turning national research into market-ready deeptech/AI companies. | H25: Organization profile | I25: 2025 | J25: 2026-07-22 | L25: DeepMinds (official) | M25: Primary | N25: https://deepminds.me/press/A-New-Era-for-Innovation-ASF-CERIST-DeepMinds-Unite-to-Build-1000-Tech-Ventures-Across-Algeria | O25: Verified | P25: [Reclassified 2026-08-01] Old Sector: 'General' -> New: 'Energy, Agriculture, Maritime, Health, Industry, Education'. Old Entity Type: 'Hub' -> New Ecosystem Type: 'Incubator/Accelerator'. [Refined 2026-08-02] Sector forced to single label 'Industry' (was multi-sector: Energy, Agriculture, Maritime, Health, Industry, Education). Maturity inferred as 'Established' (structural-type).
A26: Algeria | B26: Industry | C26: AI Incubator | D26: Incubator/Accelerator | E26: Established | F26: DjazairIA | G26: Algeria's first private incubator entirely dedicated to AI (launched Sept 2025); offers coworking, coaching, fundraising and a partnership with Toronto Metropolitan University's DMZ. | H26: Organization profile | I26: 2025-09-13 | J26: 2026-07-22 | L26: DjazairIA (official) | M26: Primary | N26: https://djazairia.com/incubateur/ | O26: Verified | P26: Confirmed via primary site + Canadian/Algerian press. [Reclassified 2026-08-01] Old Sector: 'General' -> New: 'Energy, Agriculture, Maritime, Health, Industry, Education'. Old Entity Type: 'Hub' -> New Ecosystem Type: 'R&D'. [Refined 2026-08-02] Sector forced to single label 'Education' (was multi-sector: Energy, Agriculture, Maritime, Health, Industry, Education). Maturity inferred as 'Early' (default for Startup/R&D with no funding signal). [Manual fix 2026-08-03, validation pass 2] Entity Type corrected from 'R&D' to 'Incubator/Accelerator'. Was R&D despite its own Sub-Sector explicitly saying 'AI Incubator'. [Audit 2026-08-05] Sector corrected: 'Education' -> 'Industry'. [Audit 2026-08-05] Reason: generic AI incubator -> Industry fallback, consistent with IncubMe/Leancubator [Audit 2026-08-05] Maturity corrected: 'Early' -> 'Established'. [Audit 2026-08-05] Reason: structural type per maturity rule (was left unadjusted after manual entity-type fix)
A27: Algeria | B27: Agriculture | C27: Private Incubation & African Acceleration | D27: Incubator/Accelerator | E27: Established | F27: IncubMe | G27: Private Algiers incubator/accelerator; its AFRICA by IncubMe program supports African entrepreneurs across health, renewable energy, fintech, IoT, ICT and agriculture. | H27: Organization profile | I27: Not specified | J27: 2026-07-22 | L27: IncubMe (official) | M27: Primary | N27: https://incubme.com/ | O27: Verified | P27: Africa cohort cross-checked with Ilboursa; AI one of several verticals. [Reclassified 2026-08-01] Old Sector: 'General' -> New: 'Agriculture'. Old Entity Type: 'Hub' -> New Ecosystem Type: 'Incubator/Accelerator'. [Refined 2026-08-02] Sector set to 'Agriculture'. Maturity inferred as 'Established' (structural-type).
A28: Algeria | B28: Industry | C28: Innovation Hub & Open-Innovation Programs | D28: Incubator/Accelerator | E28: Established | F28: Leancubator | G28: Algiers innovation hub implementing national programs (Kick-Start with Algeria Venture and the Knowledge Economy Ministry), Algeria Startup Challenge and EU-funded incubation; ranked top Algerian incubator in 2025. | H28: Organization profile | I28: 2018 | J28: 2026-07-22 | L28: Leancubator (official) | M28: Primary | N28: https://leancubator.co/programs/ | O28: Verified | P28: Cross-checked with Challenge.ma coverage. [Reclassified 2026-08-01] Old Sector: 'General' -> New: 'Energy, Agriculture, Maritime, Health, Industry, Education'. Old Entity Type: 'Hub' -> New Ecosystem Type: 'Incubator/Accelerator'. [Refined 2026-08-02] Sector forced to single label 'Industry' (was multi-sector: Energy, Agriculture, Maritime, Health, Industry, Education). Maturity inferred as 'Established' (structural-type).
A29: Algeria | B29: Industry | C29: Accelerator / Incubator | D29: Incubator/Accelerator | E29: Established | F29: Sylabs | G29: Algeria's first private startup accelerator and tech hub (founded Dec 2015 in Algiers), providing coworking, incubation and the DZ Acceleration Program. | H29: Company profile | I29: 2015-12 | J29: 2026-07-27 | L29: MENAbytes | M29: Secondary | N29: https://www.menabytes.com/slyabs-algeria-startup-accelerator/ | O29: Verified | P29: Official site lists incubation/acceleration programs. [Reclassified 2026-08-01] Old Sector: 'General' -> New: 'Energy, Agriculture, Maritime, Health, Industry, Education'. Old Entity Type: 'Hub' -> New Ecosystem Type: 'Incubator/Accelerator'. [Refined 2026-08-02] Sector forced to single label 'Industry' (was multi-sector: Energy, Agriculture, Maritime, Health, Industry, Education). Maturity inferred as 'Established' (structural-type).
A30: Algeria | B30: Industry | C30: Data Center / Infrastructure | D30: Other initiatives | E30: Early | F30: AI Data Center in Oran (Akid Lotfi) | G30: Government-backed AI-dedicated data centre whose foundation stone was laid March 2025 in Oran, to be fitted with latest-generation GPUs. | H30: News | I30: 2025-03 | J30: 2026-07-22 | L30: Data Center Dynamics | M30: Primary (News) | N30: https://www.datacenterdynamics.com/en/news/algerian-govt-breaks-ground-on-ai-data-center-in-oran/ | O30: Verified | P30: Oracle hosting role cross-checked via Data Center Dynamics. [Reclassified 2026-08-01] Old Sector: 'Enterprise AI' -> New: 'Energy, Agriculture, Maritime, Health, Industry, Education'. Old Entity Type: 'Hub' -> New Ecosystem Type: 'Other initiatives'. [Refined 2026-08-02] Sector forced to single label 'Industry' (was multi-sector: Energy, Agriculture, Maritime, Health, Industry, Education). Maturity inferred as 'Early' (default for Startup/R&D with no funding signal).
A31: Algeria | B31: Maritime | C31: Customs & port trade facilitation AI | D31: Other initiatives | E31: Early | F31: ALCES - Algerian Customs digital clearance & AI risk-management system | G31: Digital customs information system launched in late 2023 by the Direction Générale des Douanes: online declarations and payments, real-time cargo tracking, and AI-based risk management that analyzes data in real time to detect anomalies and target suspicious import/export operations; over 120,000 declarations processed, with single-window expansion planned for 2025. | H31: Government program | I31: 2025 | J31: 2026-08-05 | L31: Maghreb Émergent | M31: Primary (News) | N31: https://www.maghrebemergent.com/les-douanes-algeriennes-accelerent-leur-transformation-numerique-et-devoilent-alces-un-systeme-qui-revolutionne-les-formalites-commerciales/ | O31: Verified | P31: Details read directly from Maghreb Émergent article; AI risk-targeting and 120,000+ declarations figure stated there. [Added 2026-08-05 expansion pass]
A32: Algeria | B32: Industry | C32: Airport / transport AI | D32: Other initiatives | E32: Early | F32: Algiers Houari Boumediene Airport AI modernization (SGSIA) | G32: SGSIA (Algiers airport management company) announced on 14 September 2025 the integration of AI into airport operations - facial recognition, intelligent gates, body scanners, automated kiosks and contactless travel - with systems going operational in December 2025 to position Algiers as a regional hub. | H32: Corporate AI project | I32: 2025-09-14 | J32: 2026-08-05 | L32: Maghreb Émergent | M32: Primary (News) | N32: https://www.maghrebemergent.com/technologie-de-pointe-laeroport-dalger-adopte-lintelligence-artificielle-pour-ameliorer-ses-services-en-2025/ | O32: Verified | P32: Based on public statements by SGSIA CEO Mokhtar Saïd Mediouni reported by Maghreb Émergent. [Added 2026-08-05 expansion pass]
A33: Algeria | B33: Industry | C33: Sovereign AI/Cloud Developer Platform | D33: Other initiatives | E33: Early | F33: AventureCloudz | G33: Full-stack sovereign AI development platform launched 29 Apr 2026 by Djezzy, Algeria Venture and Taubyte; hosted on Djezzy cloud, offering serverless, databases, storage and AI workflows for Algerian developers. | H33: News article | I33: 2026-04-29 | J33: 2026-07-22 | L33: TechAfrica News | M33: Primary (News) | N33: https://techafricanews.com/2026/05/04/algeria-venture-djezzy-and-taubyte-launch-ai-development-platform-aventurecloudz/ | O33: Verified | P33: Cross-checked with official ac.dz and Telecompaper. [Reclassified 2026-08-01] Old Sector: 'Enterprise AI' -> New: 'Industry'. Old Entity Type: 'Hub' -> New Ecosystem Type: 'Other initiatives'. [Refined 2026-08-02] Sector set to 'Industry'. Maturity inferred as 'Early' (default for Startup/R&D with no funding signal).
A34: Algeria | B34: Education | C34: Virtual education & AI pedagogy center | D34: Other initiatives | E34: Early | F34: Centre de Technologie et d'Innovation en Systèmes d'Éducation Virtuelle (Sidi Abdallah) | G34: Algeria's first national center for technologies and innovation in virtual education systems, inaugurated 8 June 2026 at the Abdelhafid Ihaddaden scientific hub (Sidi Abdallah) by Higher Education Minister Kamel Baddari with Prof. Elias Zerhouni (project designer); provides AI-powered multilingual distance-learning platforms for a 'fourth-generation university' model. | H34: Government program | I34: 2026-06-08 | J34: 2026-08-05 | L34: Algerie360 / We Are Tech Africa | M34: Primary (News) | N34: https://www.algerie360.com/education-et-ia-lalgerie-inaugure-son-premier-centre-dapprentissage-virtuel-a-sidi-abdallah/ | O34: Verified | P34: Cross-checked two independent press reports (Algerie360, We Are Tech Africa) plus Algérie Eco and El Watan coverage of the 8 June 2026 inauguration. [Added 2026-08-05 expansion pass]
A35: Algeria | B35: Industry | C35: Telecom AI Adoption & Partnerships | D35: Other initiatives | E35: Early | F35: Djezzy (AI initiatives) | G35: Telecom operator building AI capability: ENSIA partnership (Dec 2024) for AI projects, cloud launch, open-innovation deals with Algerian AI startups (AI Grid, Capture-Doc, Intadj) and the AventureCloudz platform. | H35: News article | I35: 2024-12 | J35: 2026-07-22 | L35: Algerie Eco | M35: Primary (News) | N35: https://algerie-eco.com/2024/12/23/djezzy-sengage-dans-lere-de-lintelligence-artificielle-en-partenariat-avec-lensia/ | O35: Verified | P35: Cross-checked with TSA; covers Djezzy as corporate actor (ENSIA already in DB). [Reclassified 2026-08-01] Old Sector: 'Enterprise AI' -> New: 'Industry'. Old Entity Type: 'Hub' -> New Ecosystem Type: 'Other initiatives'. [Refined 2026-08-02] Sector set to 'Industry'. Maturity inferred as 'Early' (default for Startup/R&D with no funding signal).
A36: Algeria | B36: Energy | C36: AI for oil & gas - academia-industry link | D36: Other initiatives | E36: Early | F36: ENSIA-Sonatrach 'AI in Oil & Gas' industry engagement | G36: Open-house partnership day (12 February 2024) at the National Higher School of AI (ENSIA) with Sonatrach, InnoDevData and Qareeb, where Sonatrach presented the future of AI applications in the oil and gas sector and recruited student engagement, formalizing an energy-sector pipeline for Algeria's AI school. | H36: Partnership announcement | I36: 2024-02-12 | J36: 2026-08-05 | L36: ENSIA | M36: Primary | N36: https://www.ensia.edu.dz/fr/exploring-ai-applications-in-oil-and-gas-sector/ | O36: Verified | P36: Read directly on ENSIA's official website news page naming Sonatrach and the participating companies. [Added 2026-08-05 expansion pass]
... A70: Algeria | B70: Education | C70: AI & Data Science Degree Programs | D70: R&D | E70: Established | F70: Universite Constantine 2 - Faculte NTIC | G70: Dedicated ICT faculty offering Master programs in Data Science & Artificial Intelligence (DSIA) and Data Science & Intelligent Systems; hosts AI-active research labs (e.g. MISC). | H70: Master admissions page | I70: 2024-06 | J70: 2026-07-22 | L70: Faculte NTIC, Universite Constantine 2 (official) | M70: Primary | N70: https://facntic.univ-constantine2.dz/2024/06/28/candidatures-master-2024-2025/ | O70: Verified | P70: Official faculty page lists both AI/data-science masters. [Reclassified 2026-08-01] Old Sector: 'General' -> New: 'Education'. Old Entity Type: 'Hub' -> New Ecosystem Type: 'R&D'. [Refined 2026-08-02] Sector set to 'Industry'. Maturity inferred as 'Early' (default for Startup/R&D with no funding signal). [Audit 2026-08-05] Sector corrected: 'Industry' -> 'Education'. [Audit 2026-08-05] Reason: university faculty with degree programs [Audit 2026-08-05] Maturity corrected: 'Early' -> 'Established'. [Audit 2026-08-05] Reason: institutional R&D entity (established university faculty); the blanket Early default under-stated organizational maturity
A71: Algeria | B71: Energy | C71: Sovereign GPU/AI Cloud | D71: Startup | E71: Early | F71: AI Grid | G71: Algerian startup building sovereign, energy-efficient GPU/AI cloud infrastructure (founded by an ex-Microsoft AI speech scientist); conventions signed with Etihad Groupe at ASC (Dec 2025); works with Djezzy on AI solutions. | H71: News article | I71: 2025-12 | J71: 2026-07-22 | K71: Undisclosed | L71: Algerie Patriotique | M71: Primary (News) | N71: https://algeriepatriotique.com/2025/12/09/cybersecurite-intelligence-artificielle-et-economie-bleue-des-conventions-signees-entre-startups-et-entreprises/ | O71: Verified | P71: [Reclassified 2026-08-01] Old Sector: 'Agritech' -> New: 'Energy'. Old Entity Type: 'Startup' -> New Ecosystem Type: 'Startup'. [Refined 2026-08-02] Sector set to 'Energy'. Maturity inferred as 'Early' (default for Startup/R&D with no funding signal).
A72: Algeria | B72: Industry | C72: Applied AI / RAG | D72: Startup | E72: Early | F72: BADIS AI | G72: Sovereign-AI software editor at the Cyberparc of Sidi Abdellah (Algiers) offering OCR, RAG, AI agents and Arabic/Darija chatbots. | H72: Company profile | I72: Not specified | J72: 2026-07-22 | K72: Undisclosed | L72: BADIS AI (official) | M72: Primary | N72: https://badis.ai/ | O72: Verified | P72: [Reclassified 2026-08-01] Old Sector: 'Enterprise AI' -> New: 'Industry'. Old Entity Type: 'Startup' -> New Ecosystem Type: 'Startup'. [Refined 2026-08-02] Sector set to 'Industry'. Maturity inferred as 'Early' (default for Startup/R&D with no funding signal).
A73: Algeria | B73: Industry | C73: Fire-safety robotics | D73: Startup | E73: Early | F73: BK Fire (Icosium firefighting robot) | G73: Algiers-based fire-safety company (founded 2008, repositioned as deeptech) that developed 'Icosium', a locally built firefighting robot designed to operate in high-temperature environments too dangerous for humans, one of Algeria's few hardware-robotics ventures. | H73: Company profile | I73: 2026 | J73: 2026-08-05 | K73: Undisclosed | L73: Mag Startup | M73: Aggregator | N73: https://www.magstartup.com/10-startups-algeriennes-a-suivre-en-2026-au-dela-du-bruit/ | O73: Not yet verified | P73: Found in Mag Startup's 2026 Algerian startup roundup only; robot name and repositioning not yet cross-checked with a primary source. [Added 2026-08-05 expansion pass]
A74: Algeria | B74: Health | C74: Digital health - oncology patient services | D74: Startup | E74: Early | F74: Docteur 360 | G74: Digital health startup founded by Mehdi L. Sariak that simplifies medical appointment booking and care pathways, with a solution designed for cancer patients that won the Roche Algérie-Algeria Venture e-health award at Algiers Slush'D in January 2025. | H74: Company profile | I74: 2025-01-24 | J74: 2026-08-05 | L74: Algérie Eco / We Are Tech Africa | M74: Primary (News) | N74: https://algerie-eco.com/2025/01/24/e-sante-3-startups-algeriennes-recompensees-pour-leur-innovation/ | O74: Verified | P74: Award and oncology focus from Algérie Eco; founder profile corroborated by We Are Tech Africa - AI is not yet documented as core to the product. [Added 2026-08-05 expansion pass]
A75: Algeria | B75: Industry | C75: AI-Powered HR Matching | D75: Startup | E75: Early | F75: Emploitic | G75: Algeria's leading online recruitment platform (founded 2005), now integrating AI matching algorithms between candidate skills and job requirements while limiting discriminatory bias. | H75: News article | I75: 2026 | J75: 2026-07-22 | L75: El Watan | M75: Primary (News) | N75: https://elwatan.dz/recrutement-en-ligne-emploitic-celebre-ses-20-ans/ | O75: Verified | P75: Added to fill Algeria startup-coverage gap identified after supervisor feedback. Cross-confirmed across 7+ independent sources (TechAfrica News, Developing Telecoms, El Watan, Maghreb Emergent) all agreeing on date, partners, and product details. [Reclassified 2026-08-01] Old Sector: 'Enterprise AI' -> New: 'Industry'. Old Entity Type: 'Startup' -> New Ecosystem Type: 'Startup'. [Refined 2026-08-02] Sector set to 'Industry'. Maturity inferred as 'Early' (default for Startup/R&D with no funding signal).
A76: Algeria | B76: Agriculture | C76: Computer Vision | D76: Startup | E76: Early | F76: FarmAI (SevenG) | G76: Algerian agritech using AI computer vision and drones to automate wheat-rust detection; won 2nd prize ($100k) at Huawei Tech4Good 2023. | H76: News | I76: 2023-01 | J76: 2026-07-27 | K76: $100,000 | L76: We Are Tech Africa | M76: Primary (News) | N76: https://www.wearetech.africa/en/fils-uk/solutions/seveng-advocates-for-smart-dynamic-and-efficient-farming-with-farmai | O76: Verified | P76: Confirmed via dedicated research pass, with a caveat: reads more as a student/competition venture (2nd prize + People's Choice at Huawei Tech4Good, Jan 2023) than a scaled company. Prize amount conflicts across sources ($15,000 vs $100,000) - unresolved, flag pending a primary source. [Reclassified 2026-08-01] Old Sector: 'Agritech' -> New: 'Agriculture'. Old Entity Type: 'Startup' -> New Ecosystem Type: 'Startup'. [Refined 2026-08-02] Sector set to 'Agriculture'. Maturity inferred as 'Early' (funding<1M ($100,000)).
A77: Algeria | B77: Industry | C77: Arabic / Tamazight NLP | D77: Startup | E77: Early | F77: Fentech (Tamatech) | G77: Algerian-French AI startup that, with Prof. Merouane Debbah, built the Hadretna LLM for Algerian Darija and Tamazight using ~2 billion crowdsourced tokens. | H77: News article | I77: 2024 | J77: 2026-07-22 | K77: Undisclosed | L77: Middle East AI News | M77: Primary (News) | N77: https://www.middleeastainews.com/p/north-african-ai-large-language-model-data | O77: Verified | P77: [Pending verification] Listicle source only. [Reclassified 2026-08-01] Old Sector: 'Enterprise AI' -> New: 'Industry'. Old Entity Type: 'Startup' -> New Ecosystem Type: 'Startup'. [Refined 2026-08-02] Sector set to 'Industry'. Maturity inferred as 'Early' (default for Startup/R&D with no funding signal).
A78: Algeria | B78: Industry | C78: NLP / LLM | D78: Startup | E78: Early | F78: Hadretna | G78: Algerian AI project (Fentech, with Prof. Merouane Debbah) building an LLM for Algerian Darija and Tamazight; pre-trained on ~2 billion tokens. | H78: News | I78: 2024-08 | J78: 2026-07-26 | K78: Undisclosed | L78: Middle East AI News | M78: Secondary | N78: https://www.middleeastainews.com/p/north-african-ai-large-language-model-data | O78: Verified | P78: Company distinct from the Hadretna model; cross-checked. [Reclassified 2026-08-01] Old Sector: 'Enterprise AI' -> New: 'Industry'. Old Entity Type: 'Startup' -> New Ecosystem Type: 'Startup'. [Refined 2026-08-02] Sector set to 'Industry'. Maturity inferred as 'Early' (default for Startup/R&D with no funding signal).
A79: Algeria | B79: Industry | C79: AI Media/Brand Intelligence SaaS | D79: Startup | E79: Early | F79: Intaj Digital - RIPOST | G79: Algerian startup whose RIPOST platform (launched 18 May 2026, fully developed and hosted in Algeria) uses proprietary AI for real-time monitoring of digital conversations, sentiment analysis, predictions and a dynamic Brand Score. | H79: News article | I79: 2026-05-18 | J79: 2026-07-22 | K79: Undisclosed | L79: La Nouvelle Republique | M79: Primary (News) | N79: https://www.lnr-dz.com/2026/05/21/ooredoo-accompagne-le-lancement-de-la-solution-algerienne-innovante-de-veille-et-dintelligence-artificielle-ripost/ | O79: Verified | P79: Pre-seed led by Janngo Capital with Digital Africa. [Reclassified 2026-08-01] Old Sector: 'Enterprise AI' -> New: 'Industry'. Old Entity Type: 'Startup' -> New Ecosystem Type: 'Startup'. [Refined 2026-08-02] Sector set to 'Industry'. Maturity inferred as 'Early' (default for Startup/R&D with no funding signal).
A80: Algeria | B80: Education | C80: Edtech / Deeptech | D80: Startup | E80: Growth | F80: LabLabee | G80: Algeria-founded edtech (2021) providing virtual hands-on labs for 5G, cloud and AI/telco-AI training; raised $3.4M seed (2024) led by Reach Capital. | H80: News | I80: 2024-09 | J80: 2026-07-22 | K80: $3,400,000 | L80: Wamda | M80: Primary (News) | N80: https://www.wamda.com/2024/09/algerian-edtech-lablabee-closes-34-million-seed-round | O80: Verified | P80: [Reclassified 2026-08-01] Old Sector: 'General' -> New: 'Education'. Old Entity Type: 'Startup' -> New Ecosystem Type: 'Startup'. [Refined 2026-08-02] Sector set to 'Education'. Maturity inferred as 'Growth' (funding 1-5M ($3,400,000)).
A81: Algeria | B81: Industry | C81: Legaltech AI | D81: Startup | E81: Early | F81: Legal Doctrine | G81: Algiers legaltech (founded 2018) running Algeria's largest legal database (3M+ texts) with AI features including Themis-AI. | H81: Company profile | I81: 2018 | J81: 2026-07-22 | K81: Undisclosed | L81: Legal Doctrine (official) | M81: Primary | N81: https://legal-doctrine.com/en/about | O81: Verified | P81: [Reclassified 2026-08-01] Old Sector: 'Enterprise AI' -> New: 'Industry'. Old Entity Type: 'Startup' -> New Ecosystem Type: 'Startup'. [Refined 2026-08-02] Sector set to 'Industry'. Maturity inferred as 'Early' (default for Startup/R&D with no funding signal).
A82: Algeria | B82: Industry | C82: Online expert consulting platform | D82: Startup | E82: Early | F82: Moustachir | G82: Electronic consulting platform connecting businesses with certified experts; became the first Algerian startup listed on the Algiers Stock Exchange in early 2025, raising about 94 million DZD (~$724,000) in its IPO. | H82: Funding announcement | I82: 2025 | J82: 2026-08-05 | K82: $724,000 | L82: Mag Startup / Algeria Tech News | M82: Aggregator | N82: https://www.magstartup.com/10-startups-algeriennes-a-suivre-en-2026-au-dela-du-bruit/ | O82: Not yet verified | P82: IPO amount reported consistently by two ecosystem aggregators (Mag Startup and algeriatech.news) but not yet checked against a primary bourse source. [Added 2026-08-05 expansion pass]
A83: Algeria | B83: Industry | C83: Generative AI / Search | D83: Startup | E83: Early | F83: Nojoom.ai | G83: Self-described first fully Algerian generative-AI platform, with an Arabic AI search engine (Thuraya), academic assistant (Suhail) and financial tool (Nitaq). | H83: Company profile | I83: Not specified | J83: 2026-07-26 | K83: Undisclosed | L83: Google AI for Developers | M83: Secondary | N83: https://ai.google.dev/competition/projects/nojoomai | O83: Verified | P83: Confirmed via dedicated research pass: real Algerian Arabic generative-AI platform. [Reclassified 2026-08-01] Old Sector: 'General' -> New: 'Industry'. Old Entity Type: 'Startup' -> New Ecosystem Type: 'Startup'. [Refined 2026-08-02] Sector set to 'Education'. Maturity inferred as 'Early' (default for Startup/R&D with no funding signal). [Audit 2026-08-05] Sector corrected: 'Education' -> 'Industry'. [Audit 2026-08-05] Reason: generative-AI/search startup (horizontal) -> Industry fallback
A84: Algeria | B84: Agriculture | C84: Edge AI & smart farming (IoT) | D84: Startup | E84: Early | F84: Qareeb (Q-Farming) | G84: Algerian edge-computing/IoT startup (founded 2023) whose Q-Farming platform uses LoRa connectivity and on-device AI to monitor and automate farms from soil to harvest without cloud dependence; also offers Q-Vision surveillance and Q-Access biometric access control, serves 50+ companies and is in NVIDIA Inception, Intel Liftoff and Google for Startups programs. | H84: Company profile | I84: 2025-02 | J84: 2026-08-05 | L84: Qareeb (official site) / Arab News FR | M84: Primary | N84: https://qareeb.io/ | O84: Verified | P84: Cross-checked official qareeb.io site with Arab News FR coverage of Algerian startups at LEAP 2025 and Algeria Startup Challenge 2024 Greentech win. [Added 2026-08-05 expansion pass]
A85: Algeria | B85: Health | C85: Digital health - medical appointments | D85: Startup | E85: Early | F85: Sihatech | G85: Algerian digital-health startup digitizing physician schedules and online medical appointment booking nationwide; one of three winners of the Roche Algérie-Algeria Venture e-health innovation awards at the inaugural Algiers Slush'D (January 2025). | H85: Company profile | I85: 2025-01-24 | J85: 2026-08-05 | L85: Algérie Eco | M85: Primary (News) | N85: https://algerie-eco.com/2025/01/24/e-sante-3-startups-algeriennes-recompensees-pour-leur-innovation/ | O85: Verified | P85: Award win confirmed in Algérie Eco; platform description corroborated by Izzoran's Algerian e-health startup roundup - AI is not yet core to the product. [Added 2026-08-05 expansion pass]
A86: Algeria | B86: Industry | C86: Intelligent transport & data analytics | D86: Startup | E86: Early | F86: Smart Chiked | G86: Algerian startup specializing in intelligent transport and data analytics that built a unified ticketing system tested with tram operator SETRAM, generating about 6 million DZD per month in additional revenue via real-time data transmission; exhibited at LEAP 2025 in Riyadh. | H86: Company profile | I86: 2025-02 | J86: 2026-08-05 | L86: Arab News FR | M86: Primary (News) | N86: https://www.arabnews.fr/node/500782/%C3%A9conomie | O86: Verified | P86: Profiled by Arab News FR with SETRAM pilot revenue figures from company statements at LEAP 2025. [Added 2026-08-05 expansion pass]
A87: Algeria | B87: Energy | C87: Oil & gas drilling AI | D87: Startup | E87: Early | F87: Smart Drilling Operations | G87: Labelled Algerian startup (Startup and Projet Innovant labels) that installs downhole sensors delivering real-time drilling data and predictive analytics to anticipate drilling obstacles and cut drilling time for the petroleum industry; showcased in the Algerian pavilion at LEAP 2025 in Riyadh. | H87: Company profile | I87: 2025-02 | J87: 2026-08-05 | L87: Arab News FR | M87: Primary (News) | N87: https://www.arabnews.fr/node/500782/%C3%A9conomie | O87: Verified | P87: Profiled by Arab News FR from the official Algerian delegation at LEAP 2025. [Added 2026-08-05 expansion pass]
A88: Algeria | B88: Industry | C88: Sovereign AI Platforms | D88: Startup | E88: Early | F88: Symloop AI | G88: Algiers deep-tech AI company (founded 2012) building sovereign AI (NOOR platform: RAG, document AI, NL-to-SQL, Arabic NLP, multi-agent) for regulated industries. | H88: Company profile | I88: 2012 | J88: 2026-07-22 | K88: Undisclosed | L88: Symloop AI (official) | M88: Primary | N88: https://symloop-ai.com/en/ | O88: Verified | P88: [Reclassified 2026-08-01] Old Sector: 'Enterprise AI' -> New: 'Industry'. Old Entity Type: 'Startup' -> New Ecosystem Type: 'Startup'. [Refined 2026-08-02] Sector set to 'Industry'. Maturity inferred as 'Early' (default for Startup/R&D with no funding signal).
A89: Algeria | B89: Industry | C89: HR-tech SaaS (AI-driven payroll/HR) | D89: Startup | E89: Early | F89: Talenteo | G89: Algerian HR-tech startup founded by Tarik Metnani and Louai Djaffer offering an AI-driven SaaS platform for HR and payroll management tailored to African SMEs (150+ companies, 10,000+ active users); raised a six-figure round led by Tunisia's 216 Capital in June 2025. | H89: Funding announcement | I89: 2025-06-19 | J89: 2026-08-05 | K89: Undisclosed | L89: Wamda | M89: Primary (News) | N89: https://www.wamda.com/2025/06/algerian-startup-talenteo-raises-figure-round-backed-216-capital | O89: Verified | P89: Funding round, investor and metrics confirmed in Wamda's June 2025 report. [Added 2026-08-05 expansion pass]
A90: Algeria | B90: Education | C90: AI Education for Children (EdTech) | D90: Startup | E90: Early | F90: Tarik Education Center | G90: Algerian edtech whose Tarik platform teaches AI and programming to children (ages 4-18) through games; won 1st prize at the Arab IoT & AI Challenge at GITEX Global Dubai (Oct 2023). | H90: News article | I90: 2023-10 | J90: 2026-07-22 | K90: Undisclosed | L90: Algerie Eco | M90: Primary (News) | N90: https://www.algerie-eco.com/2023/10/18/dubai-une-startup-algerienne-primee-au-concours-arabe-dans-liot-et-lai/ | O90: Verified | P90: [Pending verification] Listicle source only. [Reclassified 2026-08-01] Old Sector: 'General' -> New: 'Education'. Old Entity Type: 'Startup' -> New Ecosystem Type: 'Startup'. [Refined 2026-08-02] Sector set to 'Education'. Maturity inferred as 'Early' (default for Startup/R&D with no funding signal).
A91: Algeria | B91: Industry | C91: Cloud Infrastructure | D91: Startup | E91: Early | F91: Taubyte | G91: Algerian startup (CEO Samy Fodil) specializing in open-source, Git-native cloud infrastructure automation. Powers AventureCloudz, a full-stack AI development platform launched April 2026 in partnership with telecom operator Djezzy and public accelerator Algeria Venture, positioned as a sovereign local alternative to foreign cloud providers (AWS, Azure, Google Cloud). | H91: News article | I91: 2026-04-29 | J91: 2026-07-24 | K91: Undisclosed | L91: Ecofin Agency | M91: Primary (News) | N91: https://www.ecofinagency.com/news-services/0205-55196-algerias-sovereign-cloud-push-targets-tech-jobs-for-young-developers | O91: Verified | P91: [Reclassified 2026-08-01] Old Sector: 'Enterprise AI' -> New: 'Industry'. Old Entity Type: 'Startup' -> New Ecosystem Type: 'Startup'. [Refined 2026-08-02] Sector set to 'Industry'. Maturity inferred as 'Early' (default for Startup/R&D with no funding signal).
A92: Algeria | B92: Industry | C92: Mobility Super-App | D92: Startup | E92: Growth | F92: TemTem | G92: Ride-hailing/delivery/e-commerce super-app (200,000+ clients, 4,000+ drivers across 21 wilayas) using AI for routing/logistics; raised $1.7M seed + $4M Series A. | H92: News / aggregator | I92: Not specified | J92: 2026-07-22 | K92: $4,000,000 | L92: Mag Startup | M92: Secondary | N92: https://www.magstartup.com/10-startups-algeriennes-a-suivre-en-2026-au-dela-du-bruit/ | O92: Verified | P92: [Pending verification] AI-core classification via secondary sources. [Reclassified 2026-08-01] Old Sector: 'Fintech' -> New: 'Industry'. Old Entity Type: 'Startup' -> New Ecosystem Type: 'Startup'. [Refined 2026-08-02] Sector set to 'Industry'. Maturity inferred as 'Growth' (funding 1-5M ($4,000,000)). [Web re-verification 2026-08-05] Status 'Not yet verified' -> 'Verified'. MENAbytes, Wamda, Disrupt Africa and Ventureburn all covered TemTem's $4M Series A (Sept 2019, then Algeria's largest), plus its later super-app pivot (temtem One). Confirming source: https://www.menabytes.com/temtem-series-a/ Correction noted: Funding figures date to 2019 (seed + $4M Series A), not recent; the cited Mag Startup 2026 blog is secondary.
A93: Algeria | B93: Industry | C93: Travel-Tech | D93: Startup | E93: Established | F93: VOLZ | G93: Travel-booking platform letting users book flights and pay in Algerian dinars; closed a $5M Series A (Dec 2025), first exit for the Algerian Startup Fund. | H93: News article | I93: 2025-12 | J93: 2026-07-22 | K93: $5,000,000 | L93: Technext | M93: Primary (News) | N93: https://technext24.com/2025/12/15/volz-closes-5m-series-a-largest-algeria/ | O93: Verified | P93: [Pending verification] AI-core classification via secondary only. [Reclassified 2026-08-01] Old Sector: 'Fintech' -> New: 'Industry'. Old Entity Type: 'Startup' -> New Ecosystem Type: 'Startup'. [Refined 2026-08-02] Sector set to 'Industry'. Maturity inferred as 'Established' (funding>=5M ($5,000,000)). [Web re-verification 2026-08-05] Status 'Not yet verified' -> 'Verified'. Widely covered (Wamda, WeeTracker, Launch Base Africa, allAfrica, Technext) $5M Series A in Dec 2025, described as the largest Algerian startup round and the Algerian Startup Fund's first exit; flight booking in dinars confirmed. Confirming source: https://www.wamda.com/2025/12/algeria-volz-raises-5-million-landmark-funding-round
A94: Algeria | B94: Industry | C94: Autonomous Logistics | D94: Startup | E94: Established | F94: Yassir | G94: A regional super-application deploying geospatial AI and route optimization engines for carpooling and logistics. | H94: Company Profile | I94: Not specified | J94: 2026-07-08 | K94: $150,000,000 | L94: Company website (Yassir) | M94: Primary | N94: https://yassir.com/ | O94: Verified | P94: [Reclassified 2026-08-01] Old Sector: 'Enterprise AI' -> New: 'Industry'. Old Entity Type: 'Startup' -> New Ecosystem Type: 'Startup'. [Refined 2026-08-02] Sector set to 'Industry'. Maturity inferred as 'Established' (funding>=5M ($150,000,000)).
A95: Egypt | B95: Industry | C95: Machine Learning Community Event | D95: Community/Association | E95: Established | F95: Deep Learning IndabaX Egypt | G95: Egyptian edition of the pan-African Deep Learning Indaba movement strengthening African machine learning; the 2025 edition was held 1-2 July 2025, hosted by the Academy of Scientific Research & Technology (ASRT) with a local volunteer organizing team. | H95: Event | I95: 2025-07-01 | J95: 2026-08-05 | L95: Deep Learning Indaba | M95: Primary | N95: https://deeplearningindaba.com/2025/indabax/egypt/ | O95: Verified | P95: Verified on the official Deep Learning Indaba website's IndabaX Egypt 2025 page. [Added 2026-08-05 expansion pass]
A96: Egypt | B96: Industry | C96: AI Regulation Advocacy | D96: Community/Association | E96: Established | F96: Masaar - Technology and Law Community | G96: Cairo-based technology-and-law research community that published 'Regulating Artificial Intelligence in Egypt: Proposed Standards and Principles', informing Egypt's AI regulation debate. | H96: Think tank / policy research | I96: Not specified | J96: 2026-07-22 | L96: Masaar (official) | M96: Primary | N96: https://masaar.net/en/regulating-artificial-intelligence-in-egypt-proposed-standards-and-principles/ | O96: Verified | P96: Publication verified on Masaar's own site. [Reclassified 2026-08-01] Old Sector: 'Policy' -> New: 'Industry'. Old Entity Type: 'Policy' -> New Ecosystem Type: 'Policy/Strategy'. [Refined 2026-08-02] Sector set to 'Industry'. Maturity inferred as 'Established' (structural-type). [Manual fix 2026-08-03, validation pass 2] Entity Type corrected from 'Policy/Strategy' to 'Community/Association'. Was Policy/Strategy, but the entity's own name says 'Community' and it is an advocacy community, not a policy document or government body itself.
A97: Egypt | B97: Industry | C97: National ICT/AI Exhibition | D97: Conference/Summit | E97: Established | F97: Cairo ICT (AI Everywhere / AIDC / PAFIX) | G97: Egypt's national technology exhibition; 29th edition (Nov 16-19, 2025) themed 'AI Everywhere' with a record 161,000 visitors, hosting the AI & Cloud Computing Conference (AIDC) and CBE-sponsored PAFIX. | H97: Event | I97: 2025-11-16 | J97: 2026-07-22 | L97: Egypt State Information Service | M97: Primary (Government) | N97: https://sis.gov.eg/en/media-center/events/the-29th-edition-of-the-cairo-ict-exhibition-and-conference/ | O97: Verified | P97: Verified via SIS.gov.eg and cairoict.com. [Reclassified 2026-08-01] Old Sector: 'General' -> New: 'Energy, Agriculture, Maritime, Health, Industry, Education'. Old Entity Type: 'Hub' -> New Ecosystem Type: 'Conference/Summit'. [Refined 2026-08-02] Sector forced to single label 'Industry' (was multi-sector: Energy, Agriculture, Maritime, Health, Industry, Education). Maturity inferred as 'Established' (structural-type).
A98: Egypt | B98: Energy | C98: Energy AI Conference Track | D98: Conference/Summit | E98: Established | F98: EGYPES Innovation & AI Hub (Egypt Energy Show) | G98: Dedicated innovation and artificial intelligence hub within EGYPES (Egypt Energy Show) in Cairo, showcasing AI, digitalisation and decarbonisation technologies for the oil, gas and energy industry alongside the show's strategic and technical conferences. | H98: Event | I98: 2026 | J98: 2026-08-05 | L98: EGYPES (official site) | M98: Primary | N98: https://www.egypes.com/innovation-ai-hub/ | O98: Verified | P98: Verified on the official EGYPES website's Innovation & AI Hub page. [Added 2026-08-05 expansion pass]
A99: Egypt | B99: Education | C99: Academic AI Conference & Hackathon | D99: Conference/Summit | E99: Early | F99: ICIAAI 2026 - International Conference on Innovations and Applications of AI (Damietta University) | G99: First International Conference on Innovations and Applications of Artificial Intelligence, held 13-15 July 2026 at Damietta University by its Faculty of Computers and Artificial Intelligence with IEEE Egypt Section, including a student AI hackathon on industry, healthcare, education and agriculture challenges. | H99: Event | I99: 2026-07-13 | J99: 2026-08-05 | L99: Damietta University | M99: Primary | N99: https://iciaai.du.edu.eg/hackathon | O99: Verified | P99: Verified on the official Damietta University conference site (du.edu.eg domain). [Added 2026-08-05 expansion pass]
A100: Egypt | B100: Maritime | C100: Maritime & Logistics AI Conference | D100: Conference/Summit | E100: Established | F100: MARLOG 14 - International Maritime and Logistics Conference (AI edition) | G100: 14th edition of AASTMT's annual international maritime and logistics conference, held 23-25 February 2025 in Alexandria under the theme of how artificial intelligence can change the maritime industry, with AI-in-ports case studies from Antwerp, Rotterdam, Rome and Valencia. | H100: Event | I100: 2025-02-23 | J100: 2026-08-05 | L100: ISL - Institute of Shipping Economics and Logistics | M100: Secondary | N100: https://www.isl.org/en/marlog-2025-how-ai-revolutionizing-maritime-industry | O100: Verified | P100: Confirmed via ISL participant report and AASTMT/marlog.aast.edu conference pages and Egypt's Maritime Transport Sector news. [Added 2026-08-05 expansion pass]
A101: Egypt | B101: Industry | C101: AI Industry Summit | D101: Conference/Summit | E101: Established | F101: RiseUp AI Summit | G101: RiseUp (organizer of MENA's flagship Cairo entrepreneurship summit) held Egypt's first dedicated AI industry summit (Feb 4-6, 2025, Cairo Business Park): 2,000+ participants, 50 exhibitors, Google/Microsoft/Orange presence. | H101: Event | I101: 2025-02 | J101: 2026-07-22 | L101: Daily News Egypt | M101: Primary (News) | N101: https://www.dailynewsegypt.com/2025/02/06/riseup-ai-summit-concludes-announces-egypts-first-proptech-innovation-hub/ | O101: Verified | P101: First-edition AI summit verified via Daily News Egypt. [Reclassified 2026-08-01] Old Sector: 'General' -> New: 'Energy, Agriculture, Maritime, Health, Industry, Education'. Old Entity Type: 'Hub' -> New Ecosystem Type: 'Conference/Summit'. [Refined 2026-08-02] Sector forced to single label 'Industry' (was multi-sector: Energy, Agriculture, Maritime, Health, Industry, Education). Maturity inferred as 'Established' (structural-type).
A102: Egypt | B102: Industry | C102: Tech & Investment Event | D102: Conference/Summit | E102: Established | F102: Techne Summit Alexandria | G102: Alexandria-born international technology and investment summit (since 2015), flagship of Egypt Innovation Week with 45,000+ attendees, startup showcases and investor programs. | H102: Event | I102: 2025 | J102: 2026-07-22 | L102: Techne Summit (official) | M102: Primary | N102: https://alex.technesummit.com/2025 | O102: Verified | P102: [Reclassified 2026-08-01] Old Sector: 'General' -> New: 'Energy, Agriculture, Maritime, Health, Industry, Education'. Old Entity Type: 'Hub' -> New Ecosystem Type: 'Conference/Summit'. [Refined 2026-08-02] Sector forced to single label 'Industry' (was multi-sector: Energy, Agriculture, Maritime, Health, Industry, Education). Maturity inferred as 'Established' (structural-type).
A103: Egypt | B103: Agriculture | C103: Venture Capital | D103: Funding | E103: Established | F103: Algebra Ventures | G103: Egypt's leading tech-focused VC; second fund targets fintech, agritech, edtech, logistics and healthcare startups. | H103: Fund launch | I103: 2021 | J103: 2026-07-22 | K103: $90,000,000 (fund size) | L103: TechCrunch | M103: Primary (News) | N103: https://techcrunch.com/2021/04/06/after-its-first-54m-fund-algebra-ventures-launches-another-90m-fund-for-startups-in-egypt/ | O103: Verified | P103: $90M second fund; tech focus confirmed. [Reclassified 2026-08-01] Old Sector: 'General' -> New: 'Agriculture'. Old Entity Type: 'Investor' -> New Ecosystem Type: 'Funding'. [Refined 2026-08-02] Sector set to 'Agriculture'. Maturity inferred as 'Established' (structural-type).
A104: Egypt | B104: Industry | C104: Venture Capital | D104: Funding | E104: Established | F104: Beltone Venture Capital | G104: Beltone Holding VC arm (est. 2023) managing a $30M fund (with CI Venture Capital) for early-stage Egyptian tech startups. | H104: Fund launch | I104: 2023 | J104: 2026-07-22 | K104: $30,000,000 (fund size) | L104: The Startup Scene | M104: Primary (News) | N104: https://thestartupscene.me/MenaEcosystems/Beltone-Launches-VC-Fund-to-Back-Egypt-s-Tech-Startups | O104: Verified | P104: $30M early-stage tech fund confirmed. [Reclassified 2026-08-01] Old Sector: 'General' -> New: 'Energy, Agriculture, Maritime, Health, Industry, Education'. Old Entity Type: 'Investor' -> New Ecosystem Type: 'Funding'. [Refined 2026-08-02] Sector forced to single label 'Industry' (was multi-sector: Energy, Agriculture, Maritime, Health, Industry, Education). Maturity inferred as 'Established' (structural-type).
A105: Egypt | B105: Industry | C105: AI Talent Development | D105: Funding | E105: Established | F105: Digital Egypt Builders Initiative (DEBI) | G105: MCIT flagship scholarship (Sept 2020) granting ~1,000 top graduates annually a state-funded professional master's in AI/data science, cybersecurity, robotics and digital arts. | H105: Government program | I105: 2020-09 | J105: 2026-07-22 | L105: MCIT | M105: Primary (Government) | N105: https://mcit.gov.eg/en/Human_Capacity/MCIT/Digital_Egypt_Builders_Initiative | O105: Verified | P105: Verified on official MCIT page; Microsoft partnership corroborated. [Reclassified 2026-08-01] Old Sector: 'Policy' -> New: 'Industry'. Old Entity Type: 'Policy' -> New Ecosystem Type: 'Funding'. [Refined 2026-08-02] Sector set to 'Industry'. Maturity inferred as 'Established' (structural-type).
A106: Egypt | B106: Agriculture | C106: Venture Capital | D106: Funding | E106: Established | F106: DisrupTech Ventures | G106: ~$36M Cairo fund focused on fintech and digital services; portfolio spans embedded finance, lending, insurtech, agritech and AI. | H106: Investor profile | I106: Not specified | J106: 2026-07-22 | L106: DisrupTech Ventures | M106: Primary | N106: https://www.disruptechventures.com/ | O106: Verified | P106: [Reclassified 2026-08-01] Old Sector: 'General' -> New: 'Agriculture'. Old Entity Type: 'Investor' -> New Ecosystem Type: 'Funding'. [Refined 2026-08-02] Sector set to 'Agriculture'. Maturity inferred as 'Established' (structural-type).
A107: Egypt | B107: Industry | C107: Fintech Accelerator & VC | D107: Funding | E107: Established | F107: EFG EV Fintech | G107: JV (2017) between EFG Hermes' EFG Finance and Egypt Ventures; accelerator (up to EGP 1M with Falak) and VC arm (up to EGP 5M); Egypt's largest fintech portfolio incl. insurtech and regtech. | H107: Investor profile | I107: 2017 | J107: 2026-07-22 | L107: EFG EV Fintech (official) | M107: Primary | N107: https://www.efgev.com/about/ | O107: Verified | P107: Official site verified; JV corroborated by EFG Hermes report. [Reclassified 2026-08-01] Old Sector: 'Fintech' -> New: 'Energy, Agriculture, Maritime, Health, Industry, Education'. Old Entity Type: 'Investor' -> New Ecosystem Type: 'Funding'. [Refined 2026-08-02] Sector forced to single label 'Industry' (was multi-sector: Energy, Agriculture, Maritime, Health, Industry, Education). Maturity inferred as 'Established' (structural-type).
A108: Egypt | B108: Industry | C108: State-Backed Venture Capital | D108: Funding | E108: Established | F108: Egypt Ventures | G108: State-seeded investment firm (est. 2017 by Ministry of Investment) investing in accelerators, VCs and startups; portfolio includes MNT-Halan and AI-enabled startups like Educatly. | H108: Investor profile | I108: 2017 | J108: 2026-07-22 | L108: Egypt Ventures (official) | M108: Primary | N108: https://egyptventures.com/ | O108: Verified | P108: Verified via official site; state backing confirmed. [Reclassified 2026-08-01] Old Sector: 'General' -> New: 'Energy, Agriculture, Maritime, Health, Industry, Education'. Old Entity Type: 'Investor' -> New Ecosystem Type: 'Funding'. [Refined 2026-08-02] Sector forced to single label 'Education' (was multi-sector: Energy, Agriculture, Maritime, Health, Industry, Education). Maturity inferred as 'Established' (structural-type). [Audit 2026-08-05] Sector corrected: 'Education' -> 'Industry'. [Audit 2026-08-05] Reason: generic state VC, no education focus
A109: Egypt | B109: Industry | C109: Venture Capital | D109: Funding | E109: Established | F109: Flat6Labs | G109: Prominent seed investor and accelerator of technology startups operating structured programs across Cairo. | H109: Investment portfolio | I109: Not specified | J109: 2026-07-08 | L109: Company website (Flat6Labs) | M109: Primary | N109: https://www.flat6labs.com/ | O109: Verified | P109: Cross-checked with Telquel; distinct from Flat6Labs Morocco row. [Reclassified 2026-08-01] Old Sector: 'General' -> New: 'Energy, Agriculture, Maritime, Health, Industry, Education'. Old Entity Type: 'Investor' -> New Ecosystem Type: 'Funding'. [Refined 2026-08-02] Sector forced to single label 'Industry' (was multi-sector: Energy, Agriculture, Maritime, Health, Industry, Education). Maturity inferred as 'Established' (structural-type).
A110: Egypt | B110: Industry | C110: Fintech-focused Venture Fund | D110: Funding | E110: Established | F110: Nclude by Global Ventures | G110: Fintech fund launched by Banque Misr, National Bank of Egypt and Banque du Caire with Global Ventures; closed ~$110M. | H110: Fund launch | I110: 2022 | J110: 2026-07-22 | K110: $110,000,000 (fund size) | L110: Banque Misr (official) | M110: Primary | N110: https://www.banquemisr.com/en/Home/ABOUT-US/News/News0 | O110: Verified | P110: [Reclassified 2026-08-01] Old Sector: 'General' -> New: 'Energy, Agriculture, Maritime, Health, Industry, Education'. Old Entity Type: 'Investor' -> New Ecosystem Type: 'Funding'. [Refined 2026-08-02] Sector forced to single label 'Industry' (was multi-sector: Energy, Agriculture, Maritime, Health, Industry, Education). Maturity inferred as 'Established' (structural-type).
A111: Egypt | B111: Industry | C111: Early-Stage VC / Accelerator | D111: Funding | E111: Established | F111: Openner | G111: US-based VC running an Egypt accelerator to invest in 50 Egyptian pre-seed/seed startups (checks up to $500k); portfolio spans Egypt, US and Africa. | H111: Investor profile | I111: Not specified | J111: 2026-07-22 | L111: Egypt Today | M111: Primary (News) | N111: https://www.egypttoday.com/Article/3/91981/US-based-VC-Openner-to-launch-accelerator-invest-in-50 | O111: Verified | P111: [Reclassified 2026-08-01] Old Sector: 'General' -> New: 'Energy, Agriculture, Maritime, Health, Industry, Education'. Old Entity Type: 'Investor' -> New Ecosystem Type: 'Funding'. [Refined 2026-08-02] Sector forced to single label 'Industry' (was multi-sector: Energy, Agriculture, Maritime, Health, Industry, Education). Maturity inferred as 'Established' (structural-type).
A112: Egypt | B112: Industry | C112: Venture Capital | D112: Funding | E112: Established | F112: Sawari Ventures | G112: Cairo-based VC investing in knowledge/innovation-based tech across North Africa, including deep tech and AI. | H112: Investor profile | I112: Not specified | J112: 2026-07-22 | L112: Sawari Ventures | M112: Primary | N112: https://sawariventures.com/ | O112: Verified | P112: [Reclassified 2026-08-01] Old Sector: 'General' -> New: 'Energy, Agriculture, Maritime, Health, Industry, Education'. Old Entity Type: 'Investor' -> New Ecosystem Type: 'Funding'. [Refined 2026-08-02] Sector forced to single label 'Industry' (was multi-sector: Energy, Agriculture, Maritime, Health, Industry, Education). Maturity inferred as 'Established' (structural-type).
A113: Egypt | B113: Industry | C113: AI for FinTech | D113: Hackathons | E113: Idea-stage | F113: AI for FinTech Hackathon (CBE x DEBI) | G113: Central Bank of Egypt and MCIT launched an AI-for-FinTech hackathon under FinTech Egypt to develop DEBI students' fintech AI skills. | H113: Government program / competition | I113: 2025-10-13 | J113: 2026-07-22 | L113: Central Bank of Egypt | M113: Primary (Government) | N113: https://www.cbe.org.eg/en/news-publications/news/2025/10/13/09/55/digital-egypt-builders-initiative | O113: Verified | P113: Verified on official CBE newsroom. [Reclassified 2026-08-01] Old Sector: 'Fintech' -> New: 'Industry'. Old Entity Type: 'Policy' -> New Ecosystem Type: 'Policy/Strategy'. [Refined 2026-08-02] Sector set to 'Education'. Maturity inferred as 'Established' (structural-type). [Manual fix 2026-08-03] Entity Type corrected from 'Policy/Strategy' to 'Hackathons'. Was Policy/Strategy - the classifier matched the government-affiliation signal from 'Central Bank of Egypt' before recognizing the entity's own name and core described activity are both explicitly a hackathon. [Audit 2026-08-05] Sector corrected: 'Education' -> 'Industry'. [Audit 2026-08-05] Reason: fintech-domain hackathon -> Industry fallback [Audit 2026-08-05] Maturity corrected: 'Established' -> 'Idea-stage'. [Audit 2026-08-05] Reason: hackathon-type per maturity rule
A114: Egypt | B114: Industry | C114: AI for Climate/Mobility Hackathon | D114: Hackathons | E114: Idea-stage | F114: C(4F)2 Hackathon (Dell Technologies x MCIT) | G114: Virtual AI hackathon (March 2021) organized by Dell Technologies with Egypt's MCIT, billed as a first-of-its-kind AI hackathon in Egypt, challenging students and professionals to build AI/data-science solutions reducing CO2 emissions from vehicles and traffic, with $12,000 in prizes. | H114: Event | I114: 2021-03 | J114: 2026-08-05 | L114: Egypt National AI Portal (ai.gov.eg) | M114: Primary (Government) | N114: https://c4f2.ai.gov.eg/ | O114: Verified | P114: Hosted on Egypt's official government AI portal subdomain. [Added 2026-08-05 expansion pass]
A115: Egypt | B115: Education | C115: University AI Hackathon | D115: Hackathons | E115: Idea-stage | F115: CU-AI Nexus 2025 Hackathon | G115: Cairo University-wide AI hackathon (August-October 2025) challenging undergraduates to build AI solutions for Egypt Vision 2030 / UN SDGs across four tracks (humanities, social sciences, healthcare & life sciences, natural sciences & engineering), with EGP 50,000 prizes, seed funding and incubation for winners. | H115: Event | I115: 2025-10-18 | J115: 2026-08-05 | L115: Cairo University | M115: Primary | N115: https://ainexushack25.cu.edu.eg/ | O115: Verified | P115: Verified on the official Cairo University hackathon site (cu.edu.eg domain). [Added 2026-08-05 expansion pass]
A116: Egypt | B116: Industry | C116: National AI & IoT Innovation Program | D116: Hackathons | E116: Idea-stage | F116: Egypt AI & IoT Challenge | G116: Nationwide annual program (10th edition, 2025; originated 2016 as Egypt IoT League) run by ASRT, NTRA, IEEE TEMS Egypt and Misr El Kheir for students and startups, spanning ideation camps, mentorship and technical hackathons across 11 sectors including smart agriculture, healthcare, energy and fintech. | H116: Event | I116: 2025 | J116: 2026-08-05 | L116: Egypt AI & IoT Challenge (official site) | M116: Primary | N116: https://egypt.arabiotai.org/ | O116: Verified | P116: Verified on the official challenge website listing organizers ASRT/NTRA/IEEE TEMS/Misr El Kheir and the 2025 program timeline. [Added 2026-08-05 expansion pass]
A117: Egypt | B117: Industry | C117: Corporate AI Hackathon | D117: Hackathons | E117: Idea-stage | F117: Orange Egypt AI Hackathon 2025 | G117: Two-day AI hackathon (8-9 February 2025, 'Where Ideas Spark') at Orange Egypt's Smart Village headquarters, gathering computer science and engineering students from Cairo University, Ain Shams, ESLSCA, AUC and GUC to build AI solutions with mentorship from Orange technology leaders. | H117: Event | I117: 2025-02-08 | J117: 2026-08-05 | L117: Orange Egypt | M117: Primary | N117: https://www.orange.eg/en/about/media-center/press-kit/orange-egypt-launches-ai-hackathon-2025-862-event | O117: Verified | P117: Verified via Orange Egypt's official press release; also covered by Egypt Today and The Fast Mode. [Added 2026-08-05 expansion pass]
A118: Egypt | B118: Education | C118: University-based Accelerator | D118: Incubator/Accelerator | E118: Established | F118: AUC Venture Lab (V-Lab) | G118: Egypt's first university-based accelerator (American University in Cairo) running fintech and startup programs. | H118: Accelerator profile | I118: Not specified | J118: 2026-07-26 | L118: Failory | M118: Secondary | N118: https://www.failory.com/startups/egypt-accelerators-incubators | O118: Verified | P118: [Pending verification] Aggregator source. Confirmed via Egypt/Morocco landscape research pass: real AUC-affiliated venture lab. [Reclassified 2026-08-01] Old Sector: 'General' -> New: 'Energy, Agriculture, Maritime, Health, Industry, Education'. Old Entity Type: 'Hub' -> New Ecosystem Type: 'R&D'. [Refined 2026-08-02] Sector forced to single label 'Education' (was multi-sector: Energy, Agriculture, Maritime, Health, Industry, Education). Maturity inferred as 'Early' (default for Startup/R&D with no funding signal). [Manual fix 2026-08-03, validation pass 2] Entity Type corrected from 'R&D' to 'Incubator/Accelerator'. Was R&D despite its own Sub-Sector explicitly saying 'University-based Accelerator' - 'Lab' in the name is branding, not its functional category. [Audit 2026-08-05] Maturity corrected: 'Early' -> 'Established'. [Audit 2026-08-05] Reason: structural type per maturity rule (was left unadjusted after manual entity-type fix)
A119: Egypt | B119: Health | C119: Ecosystem Event | D119: Incubator/Accelerator | E119: Established | F119: Ai Everything MEA (Egypt Edition) | G119: The Ai Everything MEA (Egypt Edition) hub acts as a cross-sector launchpad designed to accelerate collaborative AI research, startup scaling, and digital capacity-building across the Middle East and Africa. Aligned with Egypt's National AI Strategy, the hub focuses on key innovations like AI-as-a-Service (AIaaS) infrastructure, advanced data centers optimized for high-performance workloads, and predictive AI cybersecurity systems. Additionally, it features pioneering regional applications such as deep-tech solutions for enterprise digital supply chains, specialized biotech and digital healthcare diagnostics, and local large language models (LLMs)-cementing Cairo's role as a vital center for economic and societal transformation through AI. | H119: Exhibition Records | I119: 2026 | J119: 2026-07-09 | L119: Ai Everything MEA (event site) | M119: Primary | N119: https://www.aieverything.com/ | O119: Verified | P119: [Reclassified 2026-08-01] Old Sector: 'General' -> New: 'Health'. Old Entity Type: 'Hub' -> New Ecosystem Type: 'Incubator/Accelerator'. [Refined 2026-08-02] Sector set to 'Health'. Maturity inferred as 'Established' (structural-type).
A120: Egypt | B120: Industry | C120: AI/GenAI Startup Support | D120: Incubator/Accelerator | E120: Established | F120: Creativa AI Lab (CREATIVA Innovation Hubs) | G120: MCIT's CREATIVA network of innovation hubs (19+ governorates) launched the Creativa AI Lab to support innovators and startups in AI and generative AI. | H120: Government innovation hub | I120: Not specified | J120: 2026-07-26 | L120: CREATIVA (MCIT) | M120: Primary (Government) | N120: https://creativa.gov.eg/about-creativa/ | O120: Verified | P120: [Pending verification] AI Lab launch needs a second source; distinct from Digital Egypt Innovation Centers. Confirmed via Egypt/Morocco landscape research pass: real ITIDA-run innovation hub network. [Reclassified 2026-08-01] Old Sector: 'General' -> New: 'Maritime'. Old Entity Type: 'Hub' -> New Ecosystem Type: 'Incubator/Accelerator'. [Refined 2026-08-02] Sector set to 'Industry'. Maturity inferred as 'Established' (structural-type).
A121: Egypt | B121: Industry | C121: Startup Accelerator | D121: Incubator/Accelerator | E121: Established | F121: Falak Startups | G121: Cairo-based accelerator (backed by Egypt Ventures) providing seed funding and mentorship to early-stage startups. | H121: Accelerator profile | I121: Not specified | J121: 2026-07-26 | L121: Failory | M121: Secondary | N121: https://www.failory.com/startups/egypt-accelerators-incubators | O121: Verified | P121: Listed as official Startup Tunisia partner. [Reclassified 2026-08-01] Old Sector: 'General' -> New: 'Energy, Agriculture, Maritime, Health, Industry, Education'. Old Entity Type: 'Hub' -> New Ecosystem Type: 'Incubator/Accelerator'. [Refined 2026-08-02] Sector forced to single label 'Industry' (was multi-sector: Energy, Agriculture, Maritime, Health, Industry, Education). Maturity inferred as 'Established' (structural-type).
A122: Egypt | B122: Industry | C122: Social Innovation Incubator | D122: Incubator/Accelerator | E122: Established | F122: GESR (Misr El Kheir Foundation) | G122: Misr El Kheir's incubator and innovation lab for tech and social startups (water, energy, food, health, education): 6-9 month incubation, seed funding, prototyping labs; partners incl. Vodafone, IBM, UNDP. | H122: Incubator profile | I122: Not specified | J122: 2026-07-22 | L122: GESR (official) | M122: Primary | N122: https://gesr.net/ | O122: Verified | P122: Official site verified; corroborated by Wamda and MENAbytes. [Reclassified 2026-08-01] Old Sector: 'General' -> New: 'Health'. Old Entity Type: 'Hub' -> New Ecosystem Type: 'Incubator/Accelerator'. [Refined 2026-08-02] Sector set to 'Agriculture'. Maturity inferred as 'Established' (structural-type). [Audit 2026-08-05] Sector corrected: 'Agriculture' -> 'Industry'. [Audit 2026-08-05] Reason: multi-domain social incubator (water/energy/food/health/education) -> Industry fallback
... A131: Egypt | B131: Industry | C131: Cloud & AI Region | D131: Other initiatives | E131: Early | F131: Huawei Cloud Cairo Region | G131: Huawei Cloud's public cloud region in Egypt went live in May 2024 as its first in North Africa, offering local data residency and AI services and accompanied by the release of Arabic large-language-model capabilities for the region. | H131: Company announcement | I131: 2024-05-23 | J131: 2026-08-05 | L131: Huawei | M131: Primary | N131: https://www.huawei.com/en/news/2024/5/huawei-cloud-goes-live-in-egypt | O131: Verified | P131: Official Huawei newsroom announcement; corroborated by Fierce Network and Intelligent CIO Africa coverage. [Added 2026-08-05 expansion pass]
A132: Egypt | B132: Industry | C132: AI / Cloud Data Center Infrastructure | D132: Other initiatives | E132: Idea-stage | F132: Khazna-Benya Hyperscale Data Center (Maadi Technology Park) | G132: Agreement between UAE-based Khazna Data Centers and Egypt's Benya Group (November 2023) to build Egypt's first hyperscale data center in Maadi Technology Park, Cairo, with a total investment of $250M to serve cloud and AI workloads. | H132: Company announcement | I132: 2023-11-20 | J132: 2026-08-05 | K132: $250,000,000 | L132: Khazna Data Centers | M132: Primary | N132: https://khaznadatacenters.com/press-release/khazna-data-centers-plans-to-enter-egypt-with-benya-group-to-set-up-the-countrys-first-hyper-scale-data-center-in-maadi-technology-park-with-a-total-investment-of-usd-250m/ | O132: Verified | P132: Official Khazna press release; corroborated by Telecom Review Africa and Intelligent CIO; funding figure is announced project investment. [Added 2026-08-05 expansion pass]
A133: Egypt | B133: Education | C133: Digital Skills & Innovation Hub | D133: Other initiatives | E133: Established | F133: Orange Digital Center Egypt | G133: Free digital training and innovation hub inaugurated in Cairo in December 2021 by Orange Egypt and German Development Cooperation (GIZ) - the 7th Orange Digital Center in Africa/Middle East - hosting a coding school, FabLab and startup acceleration; a further center opened in Aswan in 2026. | H133: Company program | I133: 2021-12-15 | J133: 2026-08-05 | L133: Daily News Egypt | M133: Primary (News) | N133: https://www.dailynewsegypt.com/2021/12/15/orange-egypt-german-development-cooperation-inaugurate-7th-orange-digital-center-in-africa-and-the-middle-east/ | O133: Verified | P133: Confirmed by Daily News Egypt and Orange's official Africa newsroom press release; Aswan expansion reported by Ecofin Agency (Jan 2026). [Added 2026-08-05 expansion pass]
A134: Egypt | B134: Industry | C134: Corporate AI Cloud Services | D134: Other initiatives | E134: Early | F134: TMG-Huawei AI Cloud Services Partnership | G134: Partnership announced in October 2024 between Talaat Moustafa Group and Huawei to offer AI cloud services for the first time in Egypt, bringing AI-enabled cloud capabilities to Egyptian enterprise and smart-city projects. | H134: Company announcement | I134: 2024-10 | J134: 2026-08-05 | L134: Huawei | M134: Primary | N134: https://www.huawei.com/en/news/2024/10/cloud-partnership-tmg-ceremony | O134: Verified | P134: Announced in Huawei's official newsroom (signing ceremony coverage). [Added 2026-08-05 expansion pass]
A135: Egypt | B135: Industry | C135: Shared Services AI & Automation | D135: Other initiatives | E135: Early | F135: Vodafone Intelligent Solutions (_VOIS) Egypt | G135: Vodafone's largest shared-services arm (Cairo & Alexandria, ~8,000+ employees); Egypt designated Vodafone's Center of Excellence for application development, robotics, automation and AI. | H135: Corporate center profile | I135: Not specified | J135: 2026-07-22 | L135: Cognitive Business News | M135: Secondary | N135: https://cognitivebusiness.news/vodafone-expands-its-egyptian-center-of-excellence-for-cx-ai-robotics-iot/ | O135: Verified | P135: Corroborated across multiple outlets and Vodafone careers pages. [Reclassified 2026-08-01] Old Sector: 'Enterprise AI' -> New: 'Industry'. Old Entity Type: 'Hub' -> New Ecosystem Type: 'Other initiatives'. [Refined 2026-08-02] Sector set to 'Industry'. Maturity inferred as 'Early' (default for Startup/R&D with no funding signal).
A136: Egypt | B136: Energy | C136: Petroleum AI Platform (JV) | D136: Policy/Strategy | E136: Idea-stage | F136: AIQ Egypt (proposed AI platform for the petroleum sector) | G136: Proposed joint venture between Egypt's Ministry of Petroleum and Abu Dhabi-based AI company AIQ (announced in talks July 2026) to create a specialized AI applications platform for Egypt's petroleum sector, combining Egypt Upstream Gateway data with AIQ tools such as ESP failure prediction up to 45 days in advance. | H136: Government program | I136: 2026-07-01 | J136: 2026-08-05 | L136: Egypt Oil & Gas | M136: Primary (News) | N136: https://egyptoil-gas.com/news/uaes-aiq-in-talks-to-launch-ai-platform-for-egypts-petroleum-sector/ | O136: Verified | P136: Reported by Egypt Oil & Gas and corroborated by Oil and Gas Advancement; still at negotiation/announcement stage. [Added 2026-08-05 expansion pass]
A137: Egypt | B137: Education | C137: Youth AI Skills | D137: Policy/Strategy | E137: Established | F137: Digital Egypt Cubs Initiative (DECI) | G137: MCIT program (May 2022, $25M initial budget) training top school students (grades 7-11) in tracks including AI and robotics; MoUs with IBM, Google, Microsoft, Valeo, Huawei. | H137: Government program | I137: 2022-05 | J137: 2026-07-22 | L137: MCIT | M137: Primary (Government) | N137: https://mcit.gov.eg/en/Human_Capacity/MCIT/Digital_Egypt_Cubs_Initiative | O137: Verified | P137: Verified on MCIT and SIS.gov.eg. [Reclassified 2026-08-01] Old Sector: 'Policy' -> New: 'Education'. Old Entity Type: 'Policy' -> New Ecosystem Type: 'Policy/Strategy'. [Refined 2026-08-02] Sector set to 'Education'. Maturity inferred as 'Established' (structural-type).
A138: Egypt | B138: Education | C138: National Tech Talent Program (AI tracks) | D138: Policy/Strategy | E138: Established | F138: Digital Egypt Pioneers Initiative (DEPI) | G138: MCIT fully-funded national training program preparing young Egyptians for digital jobs through tracks in artificial intelligence, data science, cloud computing and cybersecurity, delivered with industry partners; the program reached its fifth application round by 2026. | H138: Government program | I138: 2023-12 | J138: 2026-08-05 | L138: Assiut University (announcing MCIT program) | M138: Primary (Government) | N138: https://b.aun.edu.eg/dentistry/node/69443 | O138: Verified | P138: Confirmed via public-university announcement and MCIT's official DEPI page and social channels; distinct from DEBI/DECI already tracked. [Added 2026-08-05 expansion pass]
A139: Egypt | B139: Industry | C139: National Strategy | D139: Policy/Strategy | E139: Established | F139: Egypt National AI Strategy (MCIT) | G139: State strategy focused on capacity building, talent training and AI applications in the public sector. | H139: Strategic document (PDF) | I139: 2021-07-01 | J139: 2026-07-08 | L139: Egyptian Government (MCIT) | M139: Primary (Government) | N139: https://ai.gov.eg/Egypt%20National%20AI%20Strategy-%20English.pdf | O139: Verified | P139: Official government page on AI ecosystem priority. [Reclassified 2026-08-01] Old Sector: 'Policy' -> New: 'Energy, Agriculture, Maritime, Health, Industry, Education'. Old Entity Type: 'Policy' -> New Ecosystem Type: 'Policy/Strategy'. [Refined 2026-08-02] Sector forced to single label 'Industry' (was multi-sector: Energy, Agriculture, Maritime, Health, Industry, Education). Maturity inferred as 'Established' (structural-type).
A140: Egypt | B140: Industry | C140: National AI Strategy | D140: Policy/Strategy | E140: Established | F140: Egypt National AI Strategy - 2nd Edition (2025-2030) | G140: Second edition unveiled Jan 2025; six pillars (governance, technology, data, infrastructure, ecosystem, capacity) targeting 7.7% ICT GDP contribution, 30,000 AI experts and 250+ AI startups by 2030. | H140: Government strategy | I140: 2025-01 | J140: 2026-07-22 | L140: Government of Egypt (ai.gov.eg) | M140: Primary (Government) | N140: https://ai.gov.eg/SynchedFiles/en/Resources/AIstrategy%20English%2016-1-2025-1.pdf | O140: Verified | P140: Re-sourced: original Cambridge academic-survey citation confirmed accurate but was 2nd-hand; swapped to the primary news source the paper itself cites [Reclassified 2026-08-01] Old Sector: 'Policy' -> New: 'Energy, Agriculture, Maritime, Health, Industry, Education'. Old Entity Type: 'Policy' -> New Ecosystem Type: 'Policy/Strategy'. [Refined 2026-08-02] Sector forced to single label 'Industry' (was multi-sector: Energy, Agriculture, Maritime, Health, Industry, Education). Maturity inferred as 'Established' (structural-type).
A141: Egypt | B141: Energy | C141: Oil & Gas AI Adoption | D141: Policy/Strategy | E141: Idea-stage | F141: Egypt Petroleum Ministry - SLB AI Collaboration | G141: July 2026 initiative by Egypt's Minister of Petroleum Karim Badawi with SLB (formerly Schlumberger) to deploy AI across exploration, production and operations, including AI upgrades to the Egypt Upstream Gateway, real-time energy monitoring and methane emissions detection. | H141: Government program | I141: 2026-07-06 | J141: 2026-08-05 | L141: Egypt Oil & Gas | M141: Primary (News) | N141: https://egyptoil-gas.com/news/petroleum-and-mineral-resources-minister-explores-ai-adoption-with-slb-formerly-schlumberger-to-boost-local-oil-production/ | O141: Verified | P141: Reported by sector journal Egypt Oil & Gas; corroborated by Zawya, Arab Finance and Amwal Al Ghad. [Added 2026-08-05 expansion pass]
...

Sheet Summary
A1: Metric | B1: Count
A2: Total records | B2: =COUNTA(Dataset!A2:A638) -> 637
A4: By verification status
A5: Verified | B5: =COUNTIF(Dataset!O2:O638,"Verified") -> 565
A6: Not yet verified | B6: =COUNTIF(Dataset!O2:O638,"Not yet verified") -> 71
A7: Mismatch found | B7: =COUNTIF(Dataset!O2:O638,"Mismatch found") -> 1
A9: By country - southern shore
A10: Algeria | B10: =COUNTIF(Dataset!A2:A638,"Algeria") -> 93
A11: Egypt | B11: =COUNTIF(Dataset!A2:A638,"Egypt") -> 142
A12: Lebanon | B12: =COUNTIF(Dataset!A2:A638,"Lebanon") -> 78
A13: Morocco | B13: =COUNTIF(Dataset!A2:A638,"Morocco") -> 113
A14: Tunisia | B14: =COUNTIF(Dataset!A2:A638,"Tunisia") -> 111
A16: By country - northern shore
A17: France | B17: =COUNTIF(Dataset!A2:A638,"France") -> 40
A18: Italy | B18: =COUNTIF(Dataset!A2:A638,"Italy") -> 30
A19: Spain | B19: =COUNTIF(Dataset!A2:A638,"Spain") -> 30
A21: By sector
A22: Agriculture | B22: =COUNTIF(Dataset!B2:B638,"Agriculture") -> 41
A23: Education | B23: =COUNTIF(Dataset!B2:B638,"Education") -> 122
A24: Energy | B24: =COUNTIF(Dataset!B2:B638,"Energy") -> 22
A25: Health | B25: =COUNTIF(Dataset!B2:B638,"Health") -> 48
A26: Industry | B26: =COUNTIF(Dataset!B2:B638,"Industry") -> 390
A27: Maritime | B27: =COUNTIF(Dataset!B2:B638,"Maritime") -> 14
A29: By entity type
A30: Community/Association | B30: =COUNTIF(Dataset!D2:D638,"Community/Association") -> 19
A31: Conference/Summit | B31: =COUNTIF(Dataset!D2:D638,"Conference/Summit") -> 29
A32: Funding | B32: =COUNTIF(Dataset!D2:D638,"Funding") -> 47
A33: Hackathons | B33: =COUNTIF(Dataset!D2:D638,"Hackathons") -> 24
A34: Incubator/Accelerator | B34: =COUNTIF(Dataset!D2:D638,"Incubator/Accelerator") -> 52
A35: Other initiatives | B35: =COUNTIF(Dataset!D2:D638,"Other initiatives") -> 57
A36: Policy/Strategy | B36: =COUNTIF(Dataset!D2:D638,"Policy/Strategy") -> 84
A37: R&D | B37: =COUNTIF(Dataset!D2:D638,"R&D") -> 93
A38: Startup | B38: =COUNTIF(Dataset!D2:D638,"Startup") -> 232
A40: Maturity recorded | B40: =COUNTA(Dataset!E2:E638) -> 521

Sheet Charts
A1: Records by country
A2: Category | B2: Count
A3: Italy | B3: 30
A4: Spain | B4: 30
A5: France | B5: 40
A6: Lebanon | B6: 78
A7: Algeria | B7: 93
A8: Tunisia | B8: 111
A9: Morocco | B9: 113
A10: Egypt | B10: 142
A12: Records by entity type
A13: Category | B13: Count
A14: Community/Association | B14: 19
A15: Hackathons | B15: 24
A16: Conference/Summit | B16: 29
A17: Funding | B17: 47
A18: Incubator/Accelerator | B18: 52
A19: Other initiatives | B19: 57
A20: Policy/Strategy | B20: 84
A21: R&D | B21: 93
A22: Startup | B22: 232
A25: Records by sector
A26: Category | B26: Count
A27: Maritime | B27: 14
A28: Energy | B28: 22
A29: Agriculture | B29: 41
A30: Health | B30: 48
A31: Education | B31: 122
A32: Industry | B32: 390
A35: Records by source type
A36: Category | B36: Count
A37: Primary | B37: 218
A38: Primary (News) | B38: 214
A39: Aggregator | B39: 79
A40: Primary (Government) | B40: 54
A41: Secondary | B41: 52
A42: Aggregator (Intergovernmental) | B42: 6
A43: Primary (Intergovernmental) | B43: 5
A44: Secondary (Academic Survey) | B44: 4
A45: Primary (EU) | B45: 4
A46: Primary (Academic) | B46: 1

Sheet Change Log
A1: Change | B1: Detail
A2: Merge of the two dataset branches | B2: The five-country dataset (521 records) and the northern-Mediterranean extension (476 records) were two branches sharing 360 records, not successive versions. They were merged into a single dataset of 637 records covering eight countries. 161 records existed only in the five-country branch and 116 only in the extension (100 European plus 16 Lebanese policy and ecosystem records).
A3: Schema retained | B3: The five-country schema was kept as canonical: nine entity types, a Maturity column, and a six-value Sector column recording the application domain served. It carries more information than the extension's four entity types.
A4: Sector mapping applied to incoming records | B4: The extension's Application Sector was mapped onto the six-value Sector: Industry, Education, Agriculture, Energy and Maritime map directly; Healthcare maps to Health. Finance, Government and Cross-sector have no equivalent and were resolved per record from the technology sector and sub-sector, defaulting to Industry. This follows the existing convention, under which 31 of 38 funding records and 36 of 53 policy records were already filed as Industry. Result: 86 to Industry, 22 to Education, 8 to Health.
A5: Entity type mapping applied to incoming records | B5: Startup maps directly; Investor becomes Funding; Policy becomes Policy/Strategy. Hub was split by sub-sector: incubators and campuses to Incubator/Accelerator, research centres, supercomputing and language-model work to R&D, communities and associations to Community/Association, events to Conference/Summit, infrastructure and foundations to Other initiatives.
A6: Maturity left blank for merged records | B6: The extension did not record maturity. Rather than infer it, the 116 merged records carry a blank Maturity value, flagged in the dataset quality report. 521 of 637 records have maturity recorded.
A7: Provenance recorded per record | B7: Every merged record's Notes field records its original sector, application sector and entity type, so the mapping is reversible and auditable.
A8: Verification convention unchanged | B8: Verified records are shaded green, Not yet verified are unshaded, Mismatch found is shaded red and excluded from the search index. Current split: 565 verified, 71 not yet verified, 1 mismatch.
